Workbook
Name Gender.: #REF!
Name Relationship.: #REF!
Name YesNo.: #REF!
Name YesNo2: #REF!
Name YesNo2.: #REF!

Sheet Taxpayer Info
A1: TAXPAYER INFORMATION | B1: Please complete all information shaded orange
C5: Ignore this column for a single taxpayer
B6: TAXPAYER ONE (T1) | C6: TAXPAYER TWO (T2) | D6: GUIDANCE INFORMATION
C7: Taxpayer Two should be a defacto or spouse
C8: Otherwise use a separate checklist please
A10: Relationship of Taxpayer 2 to Taxpayer 1 | D10: Please complete this information to avoid errors.
A12: Surname / Last Name
A13: First Name
A14: Middle Name
A16: Sex
A18: Email address
A20: Mobile Phone
A22: Home Street Address Line 1 | D22: PO Boxes etc cannot be shown on a tax return
A23: Home Street Address Line 2
A24: Suburb
A25: State
A26: PostCode
A27: Country (If Not Australia)
A29: Tax File Number
A31: Date of Birth
A33: Tax Resident | B33: Yes/ No | C33: Yes/ No
A34: If NOT a tax resident all year, please | D34: Accountant needs to determine date you commenced to be a tax resident
A35: advise date residency changed : | D35: or date you ceased to be a tax resident.
A36: and reason : | D36: If resident all year ignore this question
A38: No of Children | D38: May affect some family income tests.
A40: If either of you paid child maintenance
A41: during the year - How much ? | B41: $ | C41: $ | D41: May affect some family income tests. If none paid - Ignore
A43: Tax Refunds - Bank details
A44: - BSB
A45: - Account Number
A46: - Account name/s
A48: If you are NOT completing a spouse return | D48: A spouse includes married, defacto & same sex relationships.
A49: we will require the following information | D49: Spouses MUST complete this section and it is not a optional choice
A50: - Their taxable income | C50: $
A51: - Their net rental or investment losses | C51: $
A52: - Any child maintenance they paid | C52: $
A53: - Reportable fringe benefits (PAYG Summy) | C53: $
A54: - Reportable super (PAYG Summy) | C54: $
A56: Terms & Conditions: © Consulting By PK - All rights reserved. Do not share, copy, reproduce or sell any part of this document unless you have written permission from Consulting By PK. All infringements will be prosecuted. If you are the personal owner of the Consulting By PK End User License then you may use it for your own use but not for any other purpose. Disclaimer: The opinions expressed in all material published by Consulting By PK are not to be construed as financial or investment advice nor should be relied upon for any investment activities. Consulting By PK strongly recommends that you perform your own independent research and/or seek your own legal advice before making any financial decisions. Contents of this message are of general nature only and should not be relied upon solely when making an investment decision. Consulting By PK nor any of its directors, associates, staff, or associated companies bear any liability from any actions derived from in this document. One should always seek third party investment information from relevant parties such as legal, finance, and accountancy enquiries.

Sheet T1 Income
A1: INCOME | B1: Where a YES response is provided then provide supporting costs / summary or information. Use the Additional Info worksheet
B3: Taxpayer One (T1)
A5: Occupation (Main job) | C5: xxx | I5: Guide : Avoid general terms such as
I6: teacher. Describe type of role and full
I7: details ie Primary school teacher
A9: Item 1 : SALARY & WAGES | I9: Guide : Upload copies of each PAYG Summary
A10: ABN | C10: Employer name | G10: Tax | H10: Gross | I10: Fringe Ben | J10: Reportable Super
G11: 0 | H11: 0 | I11: 0 | J11: 0
A18: Item 2 : ALLOWANCES | I18: Guide : Allowances can sometimes not be shown on a PAYG summary.
A19: Purpose | C19: Employer name | G19: Amount | I19: Overnight and travel allowances may or may not be shown on PAYG summary.
G20: $ | I20: We need to determine what the allowance/s are for, to determine if a deduction is allowed
G21: $
G22: $
A25: Item 3 : EMPLOYER LUMP SUM
A26: Did you receive a lump sum ? | G26: Yes/ No | I26: Guide : Provide PAYG Summary showing termination / redundancy
A30: Item 4 : EMPLOYER ETP (Termination Payments) | I30: Guide : Provide the ETP Payment Summary showing termination amounts
A31: Did you receive an ETP ? | G31: Yes/ No
A34: Item 5 : Government Allowances eg Newstart | I34: Guide : Centrelink no longer issues payment summaries
A35: Did you receive a Govt allowance ? | G35: Yes/ No
A36: Type :
A39: Item 6 : Government Pensions | I39: Guide : The Commonwealth no longer issues payment summaries
A40: Did you receive a Govt pension that is taxable OR exempt ? | G40: Yes/ No
A41: Type :
A44: Item 7 : Superannaution Pensions, Income Stream or Annuity Income | I44: Guide : Provide the payment summary if you were under age 60.
A45: Did you receive an annuity or super pension of ANY type ? | G45: Yes/ No | J45: If you are aged 60 or over the pension is likely exempt unless
A46: How many ? | B46: No : | J46: paid by a Commonwealth or State scheme. Provide PAYG summary for these
J47: pensions. A tax offset T2 may be available
A50: Item 8 : Superannaution Lump Sums | I50: Guide : Provide the payment summary
A51: Did you receive a super lump sum on withdrawal ? | G51: Yes/ No | J51: If you are aged 60 or over the lump sum may be a lump sum pension
J52: withdrawal. Check with your fund.
A55: Item 9 : Personal Services Income
A56: Did you work for a labour hire organisation and receive a PAYG | G56: Yes/ No | I56: Guide : Provide the payment summaries.
A57: Summary labelled as Attributed PSI
A60: Item 10: Interest earned | I60: Guide : | J60: Interest earned is taxed when received.
A61: Did you earn interest on bank accounts | G61: Yes/ No | J61: Take care to include closed / former accounts.
A62: List details below or provide a summary
B63: Bank | D63: % share | E63: Account # | G63: $ (Total not share) | H63: Wht Tax
G65: $ | H65: $
G66: $ | H66: $
G67: $ | H67: $
G68: $ | H68: $
G69: $ | H69: $
G70: $ | H70: $
G71: $ | H71: $
G72: $ | H72: $
G73: $ | H73: $
A76: Item 11: Dividends | I76: Guide : | J76: Dividends are taxable when paid or DRP shares issued.
A77: Did you earn dividend income ? | G77: Yes/ No | J77: Take care to include former shares and DRP plans or buybacks.
A78: List details below or provide a summary
A79: Company | C79: Franked Div | D79: Unfranked Div | E79: % Share | G79: $ (Total not share) | H79: Wht Tax | J79: Summarise for each company only. Ie avoid showing two payments.
J80: Show any no-TFN withholding tax if it has been deducted.
G81: $ | H81: $ | J81: If you have a report from a broker or fund manager then DO NOT complete
G82: $ | H82: $ | J82: this section. Upload the report.
G83: $ | H83: $ | J83: Reliance on ATO data can be unreliable for employee share schemes
G84: $ | H84: $ | J84: so please provide that and describe eg CBA ESS
G85: $ | H85: $
G86: $ | H86: $
G87: $ | H87: $
G88: $ | H88: $
G89: $ | H89: $
G90: $ | H90: $
G91: $ | H91: $
A94: Item 12: Employee Share Scheme Shares | I94: Guide : Provide the ESP Payment Summary from the employer
A95: Were you issued any shares in your employer organisation ? | G95: Yes/ No | J95: Warning - Many employers can be slow to provide this information.
J96: If you have employee shares issued ensure you check and provide an ESS PAYG Summary
A99: Item 13 : Partnership Income | I99: Guide : Provide copy of the partnership records and tax return
A100: Did you receive a share of income from a partnership ? | G100: Yes/ No
A103: Item 13 : Trust Income
A104: Did you have investments in units in a managed trust or stapled units? | G104: Yes/ No | I104: Guide : Provide year-end tax reports from the fund / investment manager. Often issued by late August
A105: Did you have entitlement to discretionary trust income ? | G105: Yes/ No | I105: Guide : Provide trust records or copy of trust tax return for amount distributed
A106: Did you have entitlement to a fixed / unit trust income ? | G106: Yes/ No | I106: Guide : Provide trust records or copy of trust tax return for amount distributed
I107: If you have a trust a entity checklist should be completed.
A110: Item 14 : Personal Services Income
A111: Did you receive business or contractor income through a related company (80%+) | G111: Yes/ No | I111: Guide : n/a
A114: Item 15 : Business Income
A115: Have you earned income from any sources as a sole trader, ABN etc? | G115: Yes/ No | I115: Guide : Provide business income and expense details using the specific tab in this checklist
A118: Item 17: Farm Management Deposits & Repayts
A119: Do you have eligible farm management deposits ? | G119: Yes/ No | I119: Guide : Provide details of deposits and repayments for eligible schemes
J120: Applies only to primary producers.
A123: Item 18: Capital Gains
A124: Do you have a prior year capital loss ? | G124: Yes/ No | I124: Guide : This may be shown on your prior return.
A125: Did you sell or otherwise dispose / transfer ANY items such as | G125: Yes/ No | J125: Assume such events may be a CGT event.
A126: 'shares., property etc? | J126: Please send accountant reports or other summaries or relevant records
A129: Item 19 + 20: Foreign Income
A130: Do you have a direct or indirect control of a foreign company ? | G130: Yes/ No | I130: Guide : This question must be answered
A131: Have you transferred any money or property to a foreign trust? | G131: Yes/ No | I131: Guide : This question must be answered
A132: Have you earned any income with a foreign source ? | G132: Yes/ No | I132: Guide : Provide details of overseas source income from property, shares, pension etc.
A135: Item 21: Rental Income
A136: Do you own or own a share in any rental property ? | G136: Yes/ No | I136: Guide : Complete a rental schedule for EACH property.
I137: Guide : For any property acquired during year provide loan docs, lawyers settlement sheet
I138: Guide : Provide Quantity Surveyors Report for each property
A141: Item 22: Bonus from Life Company
A142: Have you received a life or friendly society bonus? | G142: Yes/ No | I142: Guide : Provide details
A145: Item 23: Forestry Managed Scheme Income
A146: Do you have an interest in a forestry scheme that has paid income? | G146: Yes/ No | I146: Guide : Provide details incl income and deductions
A149: Item 24: Any Other Income
A150: FX Gains | G150: Yes/ No | I150: Guide : Provide details of ANY other issues that you consider could be income.
A151: Game Show winnings / Prizes | G151: Yes/ No
A152: ATO interest remission prev deducted | G152: Yes/ No
A153: Bal adj on sale of deductible assets | G153: Yes/ No
...

Sheet T2 Income
A1: INCOME | B1: Where a YES response is provided then provide supporting costs / summary or information. Use the Additional Info worksheet
B3: Taxpayer Two (T2)
A5: Occupation (Main job) | C5: xxx | I5: Guide : Avoid general terms such as
I6: teacher. Describe type of role and full
I7: details ie Primary school teacher
A9: Item 1 : SALARY & WAGES | I9: Guide : Upload copies of each PAYG Summary
A10: ABN | C10: Employer name | G10: Tax | H10: Gross | I10: Fringe Ben | J10: Reportable Super
G11: 0 | H11: 0 | I11: 0 | J11: 0
A18: Item 2 : ALLOWANCES | I18: Guide : Allowances can sometimes not be shown on a PAYG summary.
A19: Purpose | C19: Employer name | G19: Amount | I19: Overnight and travel allowances may or may not be shown on PAYG summary.
G20: $ | I20: We need to determine what the allowance/s are for, to determine if a deduction is allowed
G21: $
G22: $
A25: Item 3 : EMPLOYER LUMP SUM
A26: Did you receive a lump sum ? | G26: Yes/ No | I26: Guide : Provide PAYG Summary showing termination / redundancy
A30: Item 4 : EMPLOYER ETP (Termination Payments) | I30: Guide : Provide the ETP Payment Summary showing termination amounts
A31: Did you receive an ETP ? | G31: Yes/ No
A34: Item 5 : Government Allowances eg Newstart | I34: Guide : Centrelink no longer issues payment summaries
A35: Did you receive a Govt allowance ? | G35: Yes/ No
A36: Type :
A39: Item 6 : Government Pensions | I39: Guide : The Commonwealth no longer issues payment summaries
A40: Did you receive a Govt pension that is taxable OR exempt ? | G40: Yes/ No
A41: Type :
A44: Item 7 : Superannaution Pensions, Income Stream or Annuity Income | I44: Guide : Provide the payment summary if you were under age 60.
A45: Did you receive an annuity or super pension of ANY type ? | G45: Yes/ No | J45: If you are aged 60 or over the pension is likely exempt unless
A46: How many ? | B46: No : | J46: paid by a Commonwealth or State scheme. Provide PAYG summary for these
J47: pensions. A tax offset T2 may be available
A50: Item 8 : Superannaution Lump Sums | I50: Guide : Provide the payment summary
A51: Did you receive a super lump sum on withdrawal ? | G51: Yes/ No | J51: If you are aged 60 or over the lump sum may be a lump sum pension
J52: withdrawal. Check with your fund.
A55: Item 9 : Personal Services Income
A56: Did you work for a labour hire organisation and receive a PAYG | G56: Yes/ No | I56: Guide : Provide the payment summaries.
A57: Summary labelled as Attributed PSI
A60: Item 10: Interest earned | I60: Guide : | J60: Interest earned is taxed when received.
A61: Did you earn interest on bank accounts | G61: Yes/ No | J61: Take care to include closed / former accounts.
A62: List details below or provide a summary
B63: Bank | D63: % share | E63: Account # | G63: $ (Total not share) | H63: Wht Tax
G65: $ | H65: $
G66: $ | H66: $
G67: $ | H67: $
G68: $ | H68: $
G69: $ | H69: $
G70: $ | H70: $
G71: $ | H71: $
G72: $ | H72: $
G73: $ | H73: $
A76: Item 11: Dividends | I76: Guide : | J76: Dividends are taxable when paid or DRP shares issued.
A77: Did you earn dividend income ? | G77: Yes/ No | J77: Take care to include former shares and DRP plans or buybacks.
A78: List details below or provide a summary
A79: Company | C79: Franked Div | D79: Unfranked Div | E79: % Share | G79: $ (Total not share) | H79: Wht Tax | J79: Summarise for each company only. Ie avoid showing two payments.
J80: Show any no-TFN withholding tax if it has been deducted.
G81: $ | H81: $ | J81: If you have a report from a broker or fund manager then DO NOT complete
G82: $ | H82: $ | J82: this section. Upload the report.
G83: $ | H83: $ | J83: Reliance on ATO data can be unreliable for employee share schemes
G84: $ | H84: $ | J84: so please provide that and describe eg CBA ESS
G85: $ | H85: $
G86: $ | H86: $
G87: $ | H87: $
G88: $ | H88: $
G89: $ | H89: $
G90: $ | H90: $
G91: $ | H91: $
A94: Item 12: Employee Share Scheme Shares | I94: Guide : Provide the ESP Payment Summary from the employer
A95: Were you issued any shares in your employer organisation ? | G95: Yes/ No | J95: Warning - Many employers can be slow to provide this information.
J96: If you have employee shares issued ensure you check and provide an ESS PAYG Summary
A99: Item 13 : Partnership Income | I99: Guide : Provide copy of the partnership records and tax return
A100: Did you receive a share of income from a partnership ? | G100: Yes/ No
A103: Item 13 : Trust Income
A104: Did you have investments in units in a managed trust or stapled units? | G104: Yes/ No | I104: Guide : Provide year-end tax reports from the fund / investment manager. Often issued by late August
A105: Did you have entitlement to discretionary trust income ? | G105: Yes/ No | I105: Guide : Provide trust records or copy of trust tax return for amount distributed
A106: Did you have entitlement to a fixed / unit trust income ? | G106: Yes/ No | I106: Guide : Provide trust records or copy of trust tax return for amount distributed
I107: If you have a trust a entity checklist should be completed.
A110: Item 14 : Personal Services Income
A111: Did you receive business or contractor income through a related company (80%+) | G111: Yes/ No | I111: Guide : n/a
A114: Item 15 : Business Income
A115: Have you earned income from any sources as a sole trader, ABN etc? | G115: Yes/ No | I115: Guide : Provide business income and expense details using the specific tab in this checklist
A118: Item 17: Farm Management Deposits & Repayts
A119: Do you have eligible farm management deposits ? | G119: Yes/ No | I119: Guide : Provide details of deposits and repayments for eligible schemes
J120: Applies only to primary producers.
A123: Item 18: Capital Gains
A124: Do you have a prior year capital loss ? | G124: Yes/ No | I124: Guide : This may be shown on your prior return.
A125: Did you sell or otherwise dispose / transfer ANY items such as | G125: Yes/ No | J125: Assume such events may be a CGT event.
A126: 'shares., property etc? | J126: Please send accountant reports or other summaries or relevant records
A129: Item 19 + 20: Foreign Income
A130: Do you have a direct or indirect control of a foreign company ? | G130: Yes/ No | I130: Guide : This question must be answered
A131: Have you transferred any money or property to a foreign trust? | G131: Yes/ No | I131: Guide : This question must be answered
A132: Have you earned any income with a foreign source ? | G132: Yes/ No | I132: Guide : Provide details of overseas source income from property, shares, pension etc.
A135: Item 21: Rental Income
A136: Do you own or own a share in any rental property ? | G136: Yes/ No | I136: Guide : Complete a rental schedule for EACH property.
I137: Guide : For any property acquired during year provide loan docs, lawyers settlement sheet
I138: Guide : Provide Quantity Surveyors Report for each property
A141: Item 22: Bonus from Life Company
A142: Have you received a life or friendly society bonus? | G142: Yes/ No | I142: Guide : Provide details
A145: Item 23: Forestry Managed Scheme Income
A146: Do you have an interest in a forestry scheme that has paid income? | G146: Yes/ No | I146: Guide : Provide details incl income and deductions
A149: Item 24: Any Other Income
A150: FX Gains | G150: Yes/ No | I150: Guide : Provide details of ANY other issues that you consider could be income.
A151: Game Show winnings / Prizes | G151: Yes/ No
A152: ATO interest remission prev deducted | G152: Yes/ No
A153: Bal adj on sale of deductible assets | G153: Yes/ No
...

Sheet T1 Deductions
A1: DEDUCTIONS | B1: Where a YES response is provided then provide supporting costs / summary or information. Use the Additional Info worksheet
B3: Taxpayer One (T1)
A5: Unless otherwise stated where all deductions exceed $300 ALL claims must be supported by evidence
A7: Item D1 : Work Related Car Use
A8: Do you use your car for work related purposes ? | G8: Yes/ No | I8: Guide : | J8: Provide details to assist deduction calulations based on an eligible method.
A9: Explanation of your car use | J9: Show ONLY employment related use at this section
A13: A. Cents per KM. Limit 5,000 km per car. | I13: Guide : | J13: No logbook needed. Diary or other reasonable record or calc of trips
A14: Car Rego # | J14: Rate is now a standard fixed rate of 66cents. Engine size is not required.
A15: No of work KMs | J15: Tip : Max 5,000km per vehicle. Two or more vehicles may be eligible
A16: Was all the travel in one car ? | C16: Yes or No ?
A17: Method used to determine | C17: Diary, etc calculation
A19: B. Logbook Method | C19: Refer to summary below | I19: Guide : | J19: Current logbook needed. Ie within 4 years for min 12 weeks.
J20: Send accountant copy of logbook, Depreciation, loan interest, fuel, repairs, rego, insurances etc
J21: Complete the summary below (this tab)
A24: Item D2 : Work Related Travel (Excl car) | G24: Yes/ No | I24: Guide : | J24: If claim is made using reasonable allowances you MUST have stayed
A25: Deduction based on reasonable allowance limits ? | E25: Yes/ No | J25: in a hotel, motel or similar accomodation. Provide details
A26: If no, provide summary of all travel costs not reimbursed. | J26: Travel between home and work is not eligible (ie FIFO workers)
A27: Include work related TOLLS here. Not travel to/from work
A30: Item D3 : Work Related Uniform, Protective / Specific Clothing + laundry | G30: Yes/ No | I30: Guide : | J30: Ordinary work clothes not eligible. Plain uniform not eligible (ie white shirt)
A31: Replacements ? | C31: Yes/ No
A32: Laundry of uniform ? | C32: Yes/ No
A35: Item D4 : Work Related Self Education Expenses | G35: Yes/ No | I35: Guide : | J35: Not a preliminary course of study.
A39: Item D5 : All Other Work Related Expenses | G39: Yes/ No | I39: Guide : | J39: For any items costing $300+ they may need to be depreciated. Please complete D6
A42: Item D6 : Low Value Pool | G42: Yes/ No | I42: Guide : | J42: Depreciable work use items from a prior year or acquired this year.
J43: Provide details of assets costing both under and over $300 and the date / cost
J44: Do not provide property depreciation information here.
A47: Item D7 : Interest Deductions | G47: Yes/ No | I47: Guide : | J47: Do not include interest to acquire shares held for profit. Include as a CGT related cost.
A50: Item D8 : Dividend Deductions | G50: Yes/ No | I50: Guide : | J50: N/a
A53: Item D9 : Gifts / Donations | G53: Yes/ No | I53: Guide : | J53: Check receipts. Is it tax deductible ? If any are $1,000 or more please send accountant the receipt
J54: No art unions, auction events, pens, raffles or similar costs. These are not donations.
A57: Item D10 : Costs of Managing tax Affairs | G57: Yes/ No | I57: Guide : | J57: Payments made during year for tax prep or advice incl a Quantity Surveyor report
J58: Or include QS report fee costs with the rental property.
J59: Software, travel and similar costs may be eligible.
A62: Item D11 : Undeducted Purchase Price - Foreign Pension / Annuity | G62: Yes/ No | I62: Guide : | J62: Many overseas pensions include an element of personal savings. This reduces the
J63: taxable amount of the pension or annuity. Provide details often shown on pension records.
J64: Does not apply to Australian age or super pensions - Only foreign pensions
A67: Item D12 : Personal Super Contributions | G67: Yes/ No | I67: Guide : | J67: Employee taxpayers may not be eligible to claim this deduction
A68: Did you contribute to super (not salary sacrifice) | J68: Specific rules require a deduction notice to be held prior to lodgement. If you
J69: have made a super contribution during the year advise accountant and they can guide eligibility.
A72: Item D13 : Project Pool | G72: Yes/ No | I72: Guide : | J72: Generally a taxpayer may have been involved in a business venture for this deduction category
A75: Item D14 : Forestry Managed Investment Scheme | G75: Yes/ No | I75: Guide : | J75: The managed scheme will generally provide details of income and deductions
A78: Item D15 : Other Deductions | G78: Yes/ No | I78: Guide | J78: Provide information. Most income insurers issue a letter at end of financial year to confirm the amount due
A79: Income protection insurance, not life insurance | J79: Do not include insurances in super
A80: Election expenses
A81: Interest on ATO debts
A84: Item L1 : Prior Year Losses | G84: Yes/ No | I84: Guide : | J84: Please advise accountant if you believe prior losses are available (ie non-commercial losses etc)
A88: FURTHER INFORMATION ON D1
A90: D1 Logbook Method | C90: You MUST have and provide the logbook
A92: Car rego #
A93: Date Acquired
A94: Car Model
A95: Cost of Vehicle
A97: Depreciation | C97: $ | D97: Accountant will calculate | I97: Provide the invoice if available
A98: Interest | C98: $ | D98: Accountant will calculate | I98: Provide summary of finance terms
A99: Fuel cost | C99: $ | I99: Use either annual actual or estimate based on total spend / consumption etc
A100: Insurance | C100: $ | D100: Car insurance policy, NOT CTP | I100: Whole premium deductible when paid., or monthly when paid
A101: Rego | C101: $ | D101: Rego + CTP + Inspection costs | I101: Note : If rego paid on acquisition the whole sum (except duty) is deductible when paid
A102: Repairs | C102: $ | D102: All repairs incl service, tyres etc. NOT improvements | I102: Exclude fittings and extras. These may add to depreciation.
C104: =SUM(C97:C102) -> 0 | D104: Total Annual Cost or for period owned
A106: Logbook % | I106: Accountant will need a copy of the logbook. Estimated logbook use is NOT acceptable
A107: Date of Logbook
A109: If you changed vehicle during the year also complete new vehicle information :
A111: Car rego #
A112: Date Acquired
A113: Car Model
A114: Cost of Vehicle
A116: Depreciation | C116: $ | D116: Accountant will calculate | I116: Provide the invoice if available
A117: Interest | C117: $ | D117: Accountant will calculate | I117: Provide summary of finance terms
A118: Fuel cost | C118: $ | I118: Use either annual actual or estimate based on total spend / consumption etc
A119: Insurance | C119: $ | D119: Car insurance policy, NOT CTP | I119: Whole premium deductible when paid., or monthly when paid
A120: Rego | C120: $ | D120: Rego + CTP + Inspection costs | I120: Note : If rego paid on acquisition the whole sum (except duty) is deductible when paid
A121: Repairs | C121: $ | D121: All repairs incl service, tyres etc. NOT improvements | I121: Exclude fittings and extras. These may add to depreciation.
C123: =SUM(C116:C121) -> 0 | D123: Total Annual Cost or for period owned
A125: Logbook % | I125: Accountant will need a copy of the logbook. Estimated logbook use is NOT acceptable
A126: Date of Logbook
A128: Was the old vehicle sold / traded in ? | D128: Please enter
A129: If so provide new vehicle sale contract OR details of sales price etc
A131: Terms & Conditions: © Consulting By PK - All rights reserved. Do not share, copy, reproduce or sell any part of this document unless you have written permission from Consulting By PK. All infringements will be prosecuted. If you are the personal owner of the Consulting By PK End User License then you may use it for your own use but not for any other purpose. Disclaimer: The opinions expressed in all material published by Consulting By PK are not to be construed as financial or investment advice nor should be relied upon for any investment activities. Consulting By PK strongly recommends that you perform your own independent research and/or seek your own legal advice before making any financial decisions. Contents of this message are of general nature only and should not be relied upon solely when making an investment decision. Consulting By PK nor any of its directors, associates, staff, or associated companies bear any liability from any actions derived from in this document. One should always seek third party investment information from relevant parties such as legal, finance, and accountancy enquiries.

Sheet T2 Deductions
A1: DEDUCTIONS | B1: Where a YES response is provided then provide supporting costs / summary or information. Use the Additional Info worksheet
B3: Taxpayer Two (T2)
A5: Unless otherwise stated where all deductions exceed $300 ALL claims must be supported by evidence
A7: Item D1 : Work Related Car Use
A8: Do you use your car for work related purposes ? | G8: Yes/ No | I8: Guide : | J8: Provide details to assist deduction calulations based on an eligible method.
A9: Explanation of your car use | J9: Show ONLY employment related use at this section
A13: A. Cents per KM. Limit 5,000 km per car. | I13: Guide : | J13: No logbook needed. Diary or other reasonable record or calc of trips
A14: Car Rego # | J14: Rate is now a standard fixed rate of 66cents. Engine size is not required.
A15: No of work KMs | J15: Tip : Max 5,000km per vehicle. Two or more vehicles may be eligible
A16: Was all the travel in one car ? | C16: Yes or No ?
A17: Method used to determine | C17: Diary, etc calculation
A19: B. Logbook Method | C19: Refer to summary below | I19: Guide : | J19: Current logbook needed. Ie within 4 years for min 12 weeks.
J20: Send accountant copy of logbook, Depreciation, loan interest, fuel, repairs, rego, insurances etc
J21: Complete the summary below (this tab)
A24: Item D2 : Work Related Travel (Excl car) | G24: Yes/ No | I24: Guide : | J24: If claim is made using reasonable allowances you MUST have stayed
A25: Deduction based on reasonable allowance limits ? | E25: Yes/ No | J25: in a hotel, motel or similar accomodation. Provide details
A26: If no, provide summary of all travel costs not reimbursed. | J26: Travel between home and work is not eligible (ie FIFO workers)
A27: Include work related TOLLS here. Not travel to/from work
A30: Item D3 : Work Related Uniform, Protective / Specific Clothing + laundry | G30: Yes/ No | I30: Guide : | J30: Ordinary work clothes not eligible. Plain uniform not eligible (ie white shirt)
A31: Replacements ? | C31: Yes/ No
A32: Laundry of uniform ? | C32: Yes/ No
A35: Item D4 : Work Related Self Education Expenses | G35: Yes/ No | I35: Guide : | J35: Not a preliminary course of study.
A39: Item D5 : All Other Work Related Expenses | G39: Yes/ No | I39: Guide : | J39: For any items costing $300+ they may need to be depreciated. Please complete D6
A42: Item D6 : Low Value Pool | G42: Yes/ No | I42: Guide : | J42: Depreciable work use items from a prior year or acquired this year.
J43: Provide details of assets costing both under and over $300 and the date / cost
J44: Do not provide property depreciation information here.
A47: Item D7 : Interest Deductions | G47: Yes/ No | I47: Guide : | J47: Do not include interest to acquire shares held for profit. Include as a CGT related cost.
A50: Item D8 : Dividend Deductions | G50: Yes/ No | I50: Guide : | J50: N/a
A53: Item D9 : Gifts / Donations | G53: Yes/ No | I53: Guide : | J53: Check receipts. Is it tax deductible ? If any are $1,000 or more please send accountant the receipt
J54: No art unions, auction events, pens, raffles or similar costs. These are not donations.
A57: Item D10 : Costs of Managing tax Affairs | G57: Yes/ No | I57: Guide : | J57: Payments made during year for tax prep or advice incl a Quantity Surveyor report
J58: Or include QS report fee costs with the rental property.
J59: Software, travel and similar costs may be eligible.
A62: Item D11 : Undeducted Purchase Price - Foreign Pension / Annuity | G62: Yes/ No | I62: Guide : | J62: Many overseas pensions include an element of personal savings. This reduces the
J63: taxable amount of the pension or annuity. Provide details often shown on pension records.
J64: Does not apply to Australian age or super pensions - Only foreign pensions
A67: Item D12 : Personal Super Contributions | G67: Yes/ No | I67: Guide : | J67: Employee taxpayers may not be eligible to claim this deduction
A68: Did you contribute to super (not salary sacrifice) | J68: Specific rules require a deduction notice to be held prior to lodgement. If you
J69: have made a super contribution during the year advise accountant and they can guide eligibility.
A72: Item D13 : Project Pool | G72: Yes/ No | I72: Guide : | J72: Generally a taxpayer may have been involved in a business venture for this deduction category
A75: Item D14 : Forestry Managed Investment Scheme | G75: Yes/ No | I75: Guide : | J75: The managed scheme will generally provide details of income and deductions
A78: Item D15 : Other Deductions | G78: Yes/ No | I78: Guide | J78: Provide information. Most income insurers issue a letter at end of financial year to confirm the amount due
A79: Income protection insurance, not life insurance | J79: Do not include insurances in super
A80: Election expenses
A81: Interest on ATO debts
A84: Item L1 : Prior Year Losses | G84: Yes/ No | I84: Guide : | J84: Please advise accountant if you believe prior losses are available (ie non-commercial losses etc)
A88: FURTHER INFORMATION ON D1
A90: D1 Logbook Method | C90: You MUST have and provide the logbook
A92: Car rego #
A93: Date Acquired
A94: Car Model
A95: Cost of Vehicle
A97: Depreciation | C97: $ | D97: Accountant will calculate | I97: Provide the invoice if available
A98: Interest | C98: $ | D98: Accountant will calculate | I98: Provide summary of finance terms
A99: Fuel cost | C99: $ | I99: Use either annual actual or estimate based on total spend / consumption etc
A100: Insurance | C100: $ | D100: Car insurance policy, NOT CTP | I100: Whole premium deductible when paid., or monthly when paid
A101: Rego | C101: $ | D101: Rego + CTP + Inspection costs | I101: Note : If rego paid on acquisition the whole sum (except duty) is deductible when paid
A102: Repairs | C102: $ | D102: All repairs incl service, tyres etc. NOT improvements | I102: Exclude fittings and extras. These may add to depreciation.
C104: =SUM(C97:C102) -> 0 | D104: Total Annual Cost or for period owned
A106: Logbook % | I106: Accountant will need a copy of the logbook. Estimated logbook use is NOT acceptable
A107: Date of Logbook
A109: If you changed vehicle during the year also complete new vehicle information :
A111: Car rego #
A112: Date Acquired
A113: Car Model
A114: Cost of Vehicle
A116: Depreciation | C116: $ | D116: Accountant will calculate | I116: Provide the invoice if available
A117: Interest | C117: $ | D117: Accountant will calculate | I117: Provide summary of finance terms
A118: Fuel cost | C118: $ | I118: Use either annual actual or estimate based on total spend / consumption etc
A119: Insurance | C119: $ | D119: Car insurance policy, NOT CTP | I119: Whole premium deductible when paid., or monthly when paid
A120: Rego | C120: $ | D120: Rego + CTP + Inspection costs | I120: Note : If rego paid on acquisition the whole sum (except duty) is deductible when paid
A121: Repairs | C121: $ | D121: All repairs incl service, tyres etc. NOT improvements | I121: Exclude fittings and extras. These may add to depreciation.
C123: =SUM(C116:C121) -> 0 | D123: Total Annual Cost or for period owned
A125: Logbook % | I125: Accountant will need a copy of the logbook. Estimated logbook use is NOT acceptable
A126: Date of Logbook
A128: Was the old vehicle sold / traded in ? | D128: Please enter
A129: If so provide new vehicle sale contract OR details of sales price etc
A131: Terms & Conditions: © Consulting By PK - All rights reserved. Do not share, copy, reproduce or sell any part of this document unless you have written permission from Consulting By PK. All infringements will be prosecuted. If you are the personal owner of the Consulting By PK End User License then you may use it for your own use but not for any other purpose. Disclaimer: The opinions expressed in all material published by Consulting By PK are not to be construed as financial or investment advice nor should be relied upon for any investment activities. Consulting By PK strongly recommends that you perform your own independent research and/or seek your own legal advice before making any financial decisions. Contents of this message are of general nature only and should not be relied upon solely when making an investment decision. Consulting By PK nor any of its directors, associates, staff, or associated companies bear any liability from any actions derived from in this document. One should always seek third party investment information from relevant parties such as legal, finance, and accountancy enquiries.

Sheet Tax Offsets
A1: TAX OFFSETS | B1: Tax Offsets are a credit that reduces tax payable, if any
I3: Taxpayer One (T1) | J3: Taxpayer One (T2)
A5: Item T1 : Senior & Pensioners
A6: Eligibility is restricted to only some people who receive a Govt pension. If you have completed the | I6: Yes/ No | J6: Yes/ No
A7: pension income item accountant would calculate eligibility.
A9: Item T2 : Super Pension
A10: Eligibility is restricted to only some people who receive a Govt super pension and/or receive | I10: Yes/ No | J10: Yes/ No
A11: any other super pension before they turn age 60. This is often shown on a super pension
A12: PAYG Summary. Persons aged 60+ may be ineligible other than Govt super pensions.
A14: Item T3 : Super Contributions for spouse
A15: A tax offset may be available to some taxpayers who make a contribution to their spouse super account. | I15: Yes/ No | J15: Yes/ No
A17: Item T4 : Zone or Overseas Forces Offset
A18: Did you earn income and reside in a remote zone for 183 days + (continuity is not required) | I18: Yes/ No | J18: Yes/ No
A19: ADF personnel should provide accountant with information if they are eligible incl postcodes and dates of residency
A20: FlyIn-FlyOut workers cannot claim a zone allowance. Check locations in the above list
A22: Item T5 : Net Medical Expenses
A23: ONLY eligible for aged care services and disability support devices (eg wheelchair, CPAP etc) | I23: Yes/ No | J23: Yes/ No
A25: Item T6 : Dependent (invalid + carer offset)
A26: If you maintain a family member (incl spouse) who is an invalid or a carer you may be entitled to this | I26: Yes/ No | J26: Yes/ No
A27: tax offset.
A29: Item T7 : Landcare & Water Facilities
A30: This offset is being phased out and only a un-utilised amount that has carried forward can be claimed. | I30: Yes/ No | J30: Yes/ No
A32: Item T8/9 : Other Tax Offsets
A33: Other offsets that are refundable or non-refundable. Provide details if you consider you are eligible. | I33: Yes/ No | J33: Yes/ No
A35: Terms & Conditions: © Consulting By PK - All rights reserved. Do not share, copy, reproduce or sell any part of this document unless you have written permission from Consulting By PK. All infringements will be prosecuted. If you are the personal owner of the Consulting By PK End User License then you may use it for your own use but not for any other purpose. Disclaimer: The opinions expressed in all material published by Consulting By PK are not to be construed as financial or investment advice nor should be relied upon for any investment activities. Consulting By PK strongly recommends that you perform your own independent research and/or seek your own legal advice before making any financial decisions. Contents of this message are of general nature only and should not be relied upon solely when making an investment decision. Consulting By PK nor any of its directors, associates, staff, or associated companies bear any liability from any actions derived from in this document. One should always seek third party investment information from relevant parties such as legal, finance, and accountancy enquiries.

Sheet Additional Info T1
A1: ADDITIONAL INFO TAB - TAXPAYER ONE (T1)
A4: Enter Additional Information below here (examples provided)
A6: T1 Deductions Tab, Item D4 : Work Related Self Education Expenses
A7: Statista Subscription - Directly related to maintaining skillset related to my profession of xxx | E7: 820.51
A9: T1 Deductions Tab, Item D5 : All Other Work Related Expenses
A10: Misc items (e.g. Laundry, small items, stationery etc.) | E10: 150
A12: T1 Deductions Tab, Item D9 : Gifts / Donations
A13: Donation to registered Charity | E13: 1000
A15: T1 Deductions Tab, Item D10 : Costs of Managing tax Affairs
A16: Tax return | E16: 700
A25: Terms & Conditions: © Consulting By PK - All rights reserved. Do not share, copy, reproduce or sell any part of this document unless you have written permission from Consulting By PK. All infringements will be prosecuted. If you are the personal owner of the Consulting By PK End User License then you may use it for your own use but not for any other purpose. Disclaimer: The opinions expressed in all material published by Consulting By PK are not to be construed as financial or investment advice nor should be relied upon for any investment activities. Consulting By PK strongly recommends that you perform your own independent research and/or seek your own legal advice before making any financial decisions. Contents of this message are of general nature only and should not be relied upon solely when making an investment decision. Consulting By PK nor any of its directors, associates, staff, or associated companies bear any liability from any actions derived from in this document. One should always seek third party investment information from relevant parties such as legal, finance, and accountancy enquiries.

Sheet Additional Info T2
A1: ADDITIONAL INFO TAB - TAXPAYER TWO (T2)
A4: Enter Additional Information below here (examples provided)
A6: T1 Deductions Tab, Item D4 : Work Related Self Education Expenses
A7: Statista Subscription - Directly related to maintaining skillset related to my profession of xxx | E7: 820.51
A9: T1 Deductions Tab, Item D5 : All Other Work Related Expenses
A10: Misc items (e.g. Laundry, small items, stationery etc.) | E10: 150
A12: T1 Deductions Tab, Item D9 : Gifts / Donations
A13: Donation to registered Charity | E13: 1000
A15: T1 Deductions Tab, Item D10 : Costs of Managing tax Affairs
A16: Tax return | E16: 700
A25: Terms & Conditions: © Consulting By PK - All rights reserved. Do not share, copy, reproduce or sell any part of this document unless you have written permission from Consulting By PK. All infringements will be prosecuted. If you are the personal owner of the Consulting By PK End User License then you may use it for your own use but not for any other purpose. Disclaimer: The opinions expressed in all material published by Consulting By PK are not to be construed as financial or investment advice nor should be relied upon for any investment activities. Consulting By PK strongly recommends that you perform your own independent research and/or seek your own legal advice before making any financial decisions. Contents of this message are of general nature only and should not be relied upon solely when making an investment decision. Consulting By PK nor any of its directors, associates, staff, or associated companies bear any liability from any actions derived from in this document. One should always seek third party investment information from relevant parties such as legal, finance, and accountancy enquiries.

Sheet Business T1
A1: Business - Item 15 Taxpayer One (T1) | G1: This section should ONLY be used by individuals in Business as a sole trader. Do not include property rent here.
B4: What do we mean by business?
B5: Non-passive income that is earned by personal efforts. This may involve selling, consulting or contracting and use of a ABN
B7: Is all such income - Business Income ?
B8: No. Complex rules can sometimes treat business income as if it was personally earned. These rules are called
B9: personal service income rules (PSI). If you have PSI some deductions are limited or have special rules.
B11: If my business produces a loss - Can it offset other income ?
B12: Sometimes. Your accountant will discuss this and review eligibility. You may need to meet a test.
I14: Please complete this information
B16: P2 | D16: Describe what do you do / sell or produce ?
D20: Did the business commence this year ? | I20: Yes/ No
D21: Did the business end this year ? | I21: Yes/ No
D24: Business Trading Name
D26: ABN
D28: Address where business is conducted
I30: State | N30: PostCode
B34: Entity Type | F34: Sole Traders only
F35: All other entities use, speak to accountant seperately
B37: Trading Stock
D38: Does the business hold trading stock for sale. This may include shares regularly traded | L38: Yes/ No
D39: or other inventory for sale
B42: P8 | D42: Trading Results
D43: Provide a summary of operating income and expenses. You can provide a report from excel, send accountant the file or if you use
D44: other software (Xero, MYOB etc) reports may be of assistance.
D45: The reports should also indicate details of any assets written off or eligible for depreciation
D46: If you have trading stock provide accountant with details of the calculated VALUE of stock held at 30 June 2017
B48: Questions
N49: Responses to these questions may require accountant discussion
D50: Do you receive more than 80% of income from one source ? | L50: Yes/ No
D51: Do you operate the business from your home ? | L51: Yes/ No
D52: Is any rent for your own home shown as deductible ? | L52: Yes/ No
D53: Do your expenses include any spouse / partner payments ? | L53: Yes/ No
D54: Did you claim car costs ? | L54: Yes/ No
D55: - If so, did you adjust the deduction amount for logbook % | L55: Yes/ No
D56: Do any of the expenses include private costs or a private % | L56: Yes/ No
A58: Terms & Conditions: © Consulting By PK - All rights reserved. Do not share, copy, reproduce or sell any part of this document unless you have written permission from Consulting By PK. All infringements will be prosecuted. If you are the personal owner of the Consulting By PK End User License then you may use it for your own use but not for any other purpose. Disclaimer: The opinions expressed in all material published by Consulting By PK are not to be construed as financial or investment advice nor should be relied upon for any investment activities. Consulting By PK strongly recommends that you perform your own independent research and/or seek your own legal advice before making any financial decisions. Contents of this message are of general nature only and should not be relied upon solely when making an investment decision. Consulting By PK nor any of its directors, associates, staff, or associated companies bear any liability from any actions derived from in this document. One should always seek third party investment information from relevant parties such as legal, finance, and accountancy enquiries.

Sheet Business T2
A1: Business - Item 15 Taxpayer TWO (T2) | G1: This section should ONLY be used by individuals in Business as a sole trader. Do not include property rent here.
B4: What do we mean by business?
B5: Non-passive income that is earned by personal efforts. This may involve selling, consulting or contracting and use of a ABN
B7: Is all such income - Business Income ?
B8: No. Complex rules can sometimes treat business income as if it was personally earned. These rules are called
B9: personal service income rules (PSI). If you have PSI some deductions are limited or have special rules.
B11: If my business produces a loss - Can it offset other income ?
B12: Sometimes. Your accountant will discuss this and review eligibility. You may need to meet a test.
I14: Please complete this information
B16: P2 | D16: Describe what do you do / sell or produce ?
D20: Did the business commence this year ? | I20: Yes/ No
D21: Did the business end this year ? | I21: Yes/ No
D24: Business Trading Name
D26: ABN
D28: Address where business is conducted
I30: State | N30: PostCode
B34: Entity Type | F34: Sole Traders only
F35: All other entities use, speak to accountant seperately
B37: Trading Stock
D38: Does the business hold trading stock for sale. This may include shares regularly traded | L38: Yes/ No
D39: or other inventory for sale
B42: P8 | D42: Trading Results
D43: Provide a summary of operating income and expenses. You can provide a report from excel, send accountant the file or if you use
D44: other software (Xero, MYOB etc) reports may be of assistance.
D45: The reports should also indicate details of any assets written off or eligible for depreciation
D46: If you have trading stock provide accountant with details of the calculated VALUE of stock held at 30 June 2017
B48: Questions
N49: Responses to these questions may require accountant discussion
D50: Do you receive more than 80% of income from one source ? | L50: Yes/ No
D51: Do you operate the business from your home ? | L51: Yes/ No
D52: Is any rent for your own home shown as deductible ? | L52: Yes/ No
D53: Do your expenses include any spouse / partner payments ? | L53: Yes/ No
D54: Did you claim car costs ? | L54: Yes/ No
D55: - If so, did you adjust the deduction amount for logbook % | L55: Yes/ No
D56: Do any of the expenses include private costs or a private % | L56: Yes/ No
A58: Terms & Conditions: © Consulting By PK - All rights reserved. Do not share, copy, reproduce or sell any part of this document unless you have written permission from Consulting By PK. All infringements will be prosecuted. If you are the personal owner of the Consulting By PK End User License then you may use it for your own use but not for any other purpose. Disclaimer: The opinions expressed in all material published by Consulting By PK are not to be construed as financial or investment advice nor should be relied upon for any investment activities. Consulting By PK strongly recommends that you perform your own independent research and/or seek your own legal advice before making any financial decisions. Contents of this message are of general nature only and should not be relied upon solely when making an investment decision. Consulting By PK nor any of its directors, associates, staff, or associated companies bear any liability from any actions derived from in this document. One should always seek third party investment information from relevant parties such as legal, finance, and accountancy enquiries.

Sheet Medicare Health & Other
A1: Medicare + Private Health + HECS/HELP + Other
A4: Did you ALL have private health insurance ? | D4: Yes/ No | E4: Provide a copy of the tax report issued by the fund.
E5: This question applies to ALL persons in the taxpayer family incl T1, T2 and their dependants.
E6: If one is covered and not the other please advise this.
E7: If multiple policies are held (ie T1 / T2 each different) accountant requires BOTH policy statements.
A10: HELP / Student Debt | D10: The ATO will provide accountant with this info
A12: Terms & Conditions: © Consulting By PK - All rights reserved. Do not share, copy, reproduce or sell any part of this document unless you have written permission from Consulting By PK. All infringements will be prosecuted. If you are the personal owner of the Consulting By PK End User License then you may use it for your own use but not for any other purpose. Disclaimer: The opinions expressed in all material published by Consulting By PK are not to be construed as financial or investment advice nor should be relied upon for any investment activities. Consulting By PK strongly recommends that you perform your own independent research and/or seek your own legal advice before making any financial decisions. Contents of this message are of general nature only and should not be relied upon solely when making an investment decision. Consulting By PK nor any of its directors, associates, staff, or associated companies bear any liability from any actions derived from in this document. One should always seek third party investment information from relevant parties such as legal, finance, and accountancy enquiries.

Sheet 7 Rosella Close
A1: Property 1
A3: Estimated Cashflow before tax considerations | B3: =C86+C63 -> -5013.83
A4: Approximate refund due from ATO | B4: =-C86*C4 -> 5648.3571 | C4: 0.37 | D4: < Insert your tax rate
A5: Estimated Cashflow after tax considerations | B5: =B3+B4 -> 634.5271
A8: 7 Rosella Close, Mount Sheridan QLD 4868
F9: Guidance Notes
A11: Complete this table in full please :
A12: Date property acquired : | E12: 42394 | F12: Date settled
A13: Do you have a Quantity Surveyor Report (Depreciation Schedule)? | E13: Yes | F13: Ensure accountant is provided with this. Upload ONCE when new OR replaced
A15: If a new IP but not acquired this year, was this a former home ? | E15: Please answer
A16: If so, do you know its market value on the date it first earned rent ? | E16: Please answer | F16: This can affect CGT costbase
A18: If acquired prior to this tax year - Was property refinanced this year ? | E18: No | F18: Borrowing expenses may be impacted. Refer below
A19: If refinanced this year was the loan increased ? | E19: Please answer | F19: If so, the new loan may be deductible against the new IP or new investment. Or Non-deductible. Info reqd
A21: Is this property NRAS ? | E21: No
A22: If it is, do you have the certificate for annual incentives yet ? | E22: No
A23: What is the State Incentive Amount ? | E23: $
A24: What is the Commonwealth Tax Credit Amount ? | E24: $
A26: Since the start of the financial year have you or others ever resided within this property rent free ? | E26: No
A28: Period available to rent in Financial Year | B28: Start | C28: End | F28: Explain if not available for the whole period, Change dates please
A29: Start | B29: 43282 | C29: 43646
A31: Ownership of property | B31: % | F31: Full name/s of all owners and their % share of title is essential
A32: Name of Owner 1 | B32: 1
A33: Name of Owner 2 | B33: 0
A34: Name of Owner 3 | B34: 0
A35: Name of Owner 4 | B35: 0
B36: =SUM(B32:B35) -> 1 | F36: Must add to 100%
A39: Income and Expenses Summary for this property
A41: Rent - Collected by Agent/s | C41: 21820.36 | F41: Generally entered from annual agent summary
A42: Rent - Collected by Owner/s | C42: 0 | F42: This assists accountant to address agent fees inconsistencies etc
A43: Bond retained (damage) NOT bond received for new tenant | C43: 0 | F43: Bond retained for damage etc only. Also show repair costs below.
A44: Insurance claim for lost rent / damage etc | C44: 0 | F44: This is assessable when received. Also sho repair costs. If insurer rectified damage then ignore issue
A45: Letting or other fee paid by tenant (ie water) | C45: 0 | F45: All tenant contributions to costs are to be shown here
A46: Tenant contribution for repairs / Loss | C46: 0 | F46: Ensure the repairs etc is also shown below.
A47: Total Income | C47: =SUM(C41:C46) -> 21820.36
A51: Expenses
A52: Advertising for tenants | C52: 0
A53: Asbestos removal costs | C53: 0 | F53: A specific deduction for removing asbestos may be available
A54: Body Corp / Strata - Ordinary levies | C54: 0 | F54: Do not include strata adjustments on new property acquisition. Include below 2 lines below
A55: Body Corp / Strata - Special levies | C55: 0 | D55: NOT DEDUCTIBLE…………………. | F55: Special levies may increase QS depreciation if amended by QS after completion of works
A56: Body Corp / Strata - For newly acquired property (only) | C56: 0 | F56: New acquisition only. Include strata levy settlement adjustment from lawyers settlement here
A57: Borrowing Expenses - Annual Loyalty / Package Fee | C57: 0 | F57: Show the % of annual fee relating to discounts for this property v's others
A58: Borrowing Expenses - Monthly Fees | C58: 0 | F58: Bank lender monthly fees etc eg $8pm x 12= $96
A59: Break costs (Fixed to variable loan) | C59: 0 | F59: Deductible unless broken to dispose of property. Discuss
A60: Cleaning, waste and rubbish removal | C60: 0 | F60: Not for initial tenancy. Between or after tenancy
A61: Council rates | C61: 2624.3 | F61: Do not include rates adjustments on new acquisitions here. Include next row
A62: Council rates - For newly acquired property (only) | C62: 0 | F62: New acquisition only. Include rates adjustment from lawyers settlement here
A63: Depreciation from Quantity Surveyor report | C63: 10252 | F63: Do not include capital allowances (Div 43). Include that below.
A64: Gardens lawns and yard maintenance | C64: 0 | F64: Can include tree removal etc if existing tenancy
A65: Insurance - Building | C65: 1835.51 | F65: Include premiums paid in period. Do not adjust for period of time
A66: Insurance - Contents | C66: 0 | F66: Include premiums paid in period. Do not adjust for period of time
A67: Insurance - Landlord policy | C67: 300.21 | F67: Include premiums paid in period. Do not adjust for period of time
... A74: Pest Control | C74: 0 | F74: Do NOT show initial P&B or initial repairs here
A75: Property Agent (incl GST) incl letting fees | C75: =1855+120+197.5 -> 2172.5
A76: Repairs & Maintenance - Before tenant | C76: 0 | D76: NOT DEDUCTIBLE…………………. | F76: Initial repairs are non-deductible. May be depreciable
A77: Repairs & Maintenance incl Tenant damage / wear | C77: 2448.7 | F77: Do NOT include depreciable items replaced here
A78: Quantity Surveyor Report Fee | C78: 0 | F78: Only show cost if a new report was obtained and paid this tax year
A79: Stationery, Phone, Post etc | C79: 100
A80: Travel - Any purpose, any reason = Non-deductible | D80: NOT DEDUCTIBLE…………………. | F80: Travel cannot be included in capital costs, deductions or repair costs
A81: Water | C81: 119 | F81: Include costs paid. If tenant reimbursed include that as income. Incl QLD fee for reading
A82: Water - For newly acquired property (only) | C82: 0 | F82: New acquisition only. Include upwards water adjustment from lawyers settlement here
A83: Sundry Costs | C83: 0 | F83: Details :
A84: Total Expenses | C84: =SUM(C52:C83) -> 37086.19
A86: Estimated Profit (Loss) before tax considerations | C86: =(C47-C84) -> -15265.83
A89: Borrowing Expenses
A91: Refinance Expenses (this financial year). For new acquisitions please provide lender information instead
A92: Did you refinance a former loan ? | B92: No
A93: Is the loan amount the same as previously | B93: Yes | C93: Answers No may be incorrect unless new funds were to improve or renovate.
A94: Total loan fees incurred to refinance this | B94: $ | C94: (If the refinance was to buy a new property the costs may need be applied to that new property instead of this property)
A95: Was there a break cost for THIS loan | B95: $ | C95: Eg Break a fixed loan
A97: New finance fees - For a new property generally. If new borrowing for new IP using equity include on THAT property. Not here
A98: Total borrowing expenses | B98: $ | C98: Include ALL bank fees for the loan incl appn, broker, valuation, legals by bank and LMI. Provide accountant with lender letter
A99: Is loan term greater than 5 years ? | B99: Yes | C99: Accountant will calculate a deduction based on loan term OR 60 months (shorter) and include a schedule in return.
C100: Do NOT include stamp duty or property settlement legal costs
A102: Borrowing Expenses from prior year/s (E.g. Lenders Mortgage Insurance)
A103: What was the loan start date | B103: 25/1/2016
A104: What was the total borrowing expense at that time | B104: 5640
A107: New Costs to add to Depreciation and Cap Allowances
A108: Did you incur any costs for a NON-DEDUCTIBLE item costing $300+ or a improvement, renovations etc (not a repair) ?
A109: Add further details or a summary if required. If any costs are included on a QS report do not include them to avoid duplication
A110: Please show the installed cost. Eg Oven $800 + $300 Install = $1100
A111: Advise details: Indicate if item is second hand please
A113: What was cost for | B113: Amount | C113: Date completed
B114: $
B115: $
B116: $
B117: $
B118: $
B119: $
B120: $
A122: Terms & Conditions: © Consulting By PK - All rights reserved. Do not share, copy, reproduce or sell any part of this document unless you have written permission from Consulting By PK. All infringements will be prosecuted. If you are the personal owner of the Consulting By PK End User License then you may use it for your own use but not for any other purpose. Disclaimer: The opinions expressed in all material published by Consulting By PK are not to be construed as financial or investment advice nor should be relied upon for any investment activities. Consulting By PK strongly recommends that you perform your own independent research and/or seek your own legal advice before making any financial decisions. Contents of this message are of general nature only and should not be relied upon solely when making an investment decision. Consulting By PK nor any of its directors, associates, staff, or associated companies bear any liability from any actions derived from in this document. One should always seek third party investment information from relevant parties such as legal, finance, and accountancy enquiries.

Sheet Property 2
A1: Property 2
A3: Estimated Cashflow before tax considerations | B3: =C86+C63 -> -5013.83
A4: Approximate refund due from ATO | B4: =-C86*C4 -> 5648.3571 | C4: 0.37 | D4: < Insert your tax rate
A5: Estimated Cashflow after tax considerations | B5: =B3+B4 -> 634.5271
A8: Address
F9: Guidance Notes
A11: Complete this table in full please :
A12: Date property acquired : | E12: 42394 | F12: Date settled
A13: Do you have a Quantity Surveyor Report (Depreciation Schedule)? | E13: Yes | F13: Ensure accountant is provided with this. Upload ONCE when new OR replaced
A15: If a new IP but not acquired this year, was this a former home ? | E15: Please answer
A16: If so, do you know its market value on the date it first earned rent ? | E16: Please answer | F16: This can affect CGT costbase
A18: If acquired prior to this tax year - Was property refinanced this year ? | E18: No | F18: Borrowing expenses may be impacted. Refer below
A19: If refinanced this year was the loan increased ? | E19: Please answer | F19: If so, the new loan may be deductible against the new IP or new investment. Or Non-deductible. Info reqd
A21: Is this property NRAS ? | E21: No
A22: If it is, do you have the certificate for annual incentives yet ? | E22: No
A23: What is the State Incentive Amount ? | E23: $
A24: What is the Commonwealth Tax Credit Amount ? | E24: $
A26: Since the start of the financial year have you or others ever resided within this property rent free ? | E26: No
A28: Period available to rent in Financial Year | B28: Start | C28: End | F28: Explain if not available for the whole period, Change dates please
A29: Start | B29: 43282 | C29: 43646
A31: Ownership of property | B31: % | F31: Full name/s of all owners and their % share of title is essential
A32: Name of Owner 1 | B32: 1
A33: Name of Owner 2 | B33: 0
A34: Name of Owner 3 | B34: 0
A35: Name of Owner 4 | B35: 0
B36: =SUM(B32:B35) -> 1 | F36: Must add to 100%
A39: Income and Expenses Summary for this property
A41: Rent - Collected by Agent/s | C41: 21820.36 | F41: Generally entered from annual agent summary
A42: Rent - Collected by Owner/s | C42: 0 | F42: This assists accountant to address agent fees inconsistencies etc
A43: Bond retained (damage) NOT bond received for new tenant | C43: 0 | F43: Bond retained for damage etc only. Also show repair costs below.
A44: Insurance claim for lost rent / damage etc | C44: 0 | F44: This is assessable when received. Also sho repair costs. If insurer rectified damage then ignore issue
A45: Letting or other fee paid by tenant (ie water) | C45: 0 | F45: All tenant contributions to costs are to be shown here
A46: Tenant contribution for repairs / Loss | C46: 0 | F46: Ensure the repairs etc is also shown below.
A47: Total Income | C47: =SUM(C41:C46) -> 21820.36
A51: Expenses
A52: Advertising for tenants | C52: 0
A53: Asbestos removal costs | C53: 0 | F53: A specific deduction for removing asbestos may be available
A54: Body Corp / Strata - Ordinary levies | C54: 0 | F54: Do not include strata adjustments on new property acquisition. Include below 2 lines below
A55: Body Corp / Strata - Special levies | C55: 0 | D55: NOT DEDUCTIBLE…………………. | F55: Special levies may increase QS depreciation if amended by QS after completion of works
A56: Body Corp / Strata - For newly acquired property (only) | C56: 0 | F56: New acquisition only. Include strata levy settlement adjustment from lawyers settlement here
A57: Borrowing Expenses - Annual Loyalty / Package Fee | C57: 0 | F57: Show the % of annual fee relating to discounts for this property v's others
A58: Borrowing Expenses - Monthly Fees | C58: 0 | F58: Bank lender monthly fees etc eg $8pm x 12= $96
A59: Break costs (Fixed to variable loan) | C59: 0 | F59: Deductible unless broken to dispose of property. Discuss
A60: Cleaning, waste and rubbish removal | C60: 0 | F60: Not for initial tenancy. Between or after tenancy
A61: Council rates | C61: 2624.3 | F61: Do not include rates adjustments on new acquisitions here. Include next row
A62: Council rates - For newly acquired property (only) | C62: 0 | F62: New acquisition only. Include rates adjustment from lawyers settlement here
A63: Depreciation from Quantity Surveyor report | C63: 10252 | F63: Do not include capital allowances (Div 43). Include that below.
A64: Gardens lawns and yard maintenance | C64: 0 | F64: Can include tree removal etc if existing tenancy
A65: Insurance - Building | C65: 1835.51 | F65: Include premiums paid in period. Do not adjust for period of time
A66: Insurance - Contents | C66: 0 | F66: Include premiums paid in period. Do not adjust for period of time
A67: Insurance - Landlord policy | C67: 300.21 | F67: Include premiums paid in period. Do not adjust for period of time
... A74: Pest Control | C74: 0 | F74: Do NOT show initial P&B or initial repairs here
A75: Property Agent (incl GST) incl letting fees | C75: =1855+120+197.5 -> 2172.5
A76: Repairs & Maintenance - Before tenant | C76: 0 | D76: NOT DEDUCTIBLE…………………. | F76: Initial repairs are non-deductible. May be depreciable
A77: Repairs & Maintenance incl Tenant damage / wear | C77: 2448.7 | F77: Do NOT include depreciable items replaced here
A78: Quantity Surveyor Report Fee | C78: 0 | F78: Only show cost if a new report was obtained and paid this tax year
A79: Stationery, Phone, Post etc | C79: 100
A80: Travel - Any purpose, any reason = Non-deductible | D80: NOT DEDUCTIBLE…………………. | F80: Travel cannot be included in capital costs, deductions or repair costs
A81: Water | C81: 119 | F81: Include costs paid. If tenant reimbursed include that as income. Incl QLD fee for reading
A82: Water - For newly acquired property (only) | C82: 0 | F82: New acquisition only. Include upwards water adjustment from lawyers settlement here
A83: Sundry Costs | C83: 0 | F83: Details :
A84: Total Expenses | C84: =SUM(C52:C83) -> 37086.19
A86: Estimated Profit (Loss) before tax considerations | C86: =(C47-C84) -> -15265.83
A89: Borrowing Expenses
A91: Refinance Expenses (this financial year). For new acquisitions please provide lender information instead
A92: Did you refinance a former loan ? | B92: No
A93: Is the loan amount the same as previously | B93: Yes | C93: Answers No may be incorrect unless new funds were to improve or renovate.
A94: Total loan fees incurred to refinance this | B94: $ | C94: (If the refinance was to buy a new property the costs may need be applied to that new property instead of this property)
A95: Was there a break cost for THIS loan | B95: $ | C95: Eg Break a fixed loan
A97: New finance fees - For a new property generally. If new borrowing for new IP using equity include on THAT property. Not here
A98: Total borrowing expenses | B98: $ | C98: Include ALL bank fees for the loan incl appn, broker, valuation, legals by bank and LMI. Provide accountant with lender letter
A99: Is loan term greater than 5 years ? | B99: Yes | C99: Accountant will calculate a deduction based on loan term OR 60 months (shorter) and include a schedule in return.
C100: Do NOT include stamp duty or property settlement legal costs
A102: Borrowing Expenses from prior year/s (E.g. Lenders Mortgage Insurance)
A103: What was the loan start date | B103: 25/1/2016
A104: What was the total borrowing expense at that time | B104: 5640
A107: New Costs to add to Depreciation and Cap Allowances
A108: Did you incur any costs for a NON-DEDUCTIBLE item costing $300+ or a improvement, renovations etc (not a repair) ?
A109: Add further details or a summary if required. If any costs are included on a QS report do not include them to avoid duplication
A110: Please show the installed cost. Eg Oven $800 + $300 Install = $1100
A111: Advise details: Indicate if item is second hand please
A113: What was cost for | B113: Amount | C113: Date completed
B114: $
B115: $
B116: $
B117: $
B118: $
B119: $
B120: $
A122: Terms & Conditions: © Consulting By PK - All rights reserved. Do not share, copy, reproduce or sell any part of this document unless you have written permission from Consulting By PK. All infringements will be prosecuted. If you are the personal owner of the Consulting By PK End User License then you may use it for your own use but not for any other purpose. Disclaimer: The opinions expressed in all material published by Consulting By PK are not to be construed as financial or investment advice nor should be relied upon for any investment activities. Consulting By PK strongly recommends that you perform your own independent research and/or seek your own legal advice before making any financial decisions. Contents of this message are of general nature only and should not be relied upon solely when making an investment decision. Consulting By PK nor any of its directors, associates, staff, or associated companies bear any liability from any actions derived from in this document. One should always seek third party investment information from relevant parties such as legal, finance, and accountancy enquiries.

Sheet Property 3
A1: Property 3
A3: Estimated Cashflow before tax considerations | B3: =C86+C63 -> -5013.83
A4: Approximate refund due from ATO | B4: =-C86*C4 -> 5648.3571 | C4: 0.37 | D4: < Insert your tax rate
A5: Estimated Cashflow after tax considerations | B5: =B3+B4 -> 634.5271
A8: Address
F9: Guidance Notes
A11: Complete this table in full please :
A12: Date property acquired : | E12: 42394 | F12: Date settled
A13: Do you have a Quantity Surveyor Report (Depreciation Schedule)? | E13: Yes | F13: Ensure accountant is provided with this. Upload ONCE when new OR replaced
A15: If a new IP but not acquired this year, was this a former home ? | E15: Please answer
A16: If so, do you know its market value on the date it first earned rent ? | E16: Please answer | F16: This can affect CGT costbase
A18: If acquired prior to this tax year - Was property refinanced this year ? | E18: No | F18: Borrowing expenses may be impacted. Refer below
A19: If refinanced this year was the loan increased ? | E19: Please answer | F19: If so, the new loan may be deductible against the new IP or new investment. Or Non-deductible. Info reqd
A21: Is this property NRAS ? | E21: No
A22: If it is, do you have the certificate for annual incentives yet ? | E22: No
A23: What is the State Incentive Amount ? | E23: $
A24: What is the Commonwealth Tax Credit Amount ? | E24: $
A26: Since the start of the financial year have you or others ever resided within this property rent free ? | E26: No
A28: Period available to rent in Financial Year | B28: Start | C28: End | F28: Explain if not available for the whole period, Change dates please
A29: Start | B29: 43282 | C29: 43646
A31: Ownership of property | B31: % | F31: Full name/s of all owners and their % share of title is essential
A32: Name of Owner 1 | B32: 1
A33: Name of Owner 2 | B33: 0
A34: Name of Owner 3 | B34: 0
A35: Name of Owner 4 | B35: 0
B36: =SUM(B32:B35) -> 1 | F36: Must add to 100%
A39: Income and Expenses Summary for this property
A41: Rent - Collected by Agent/s | C41: 21820.36 | F41: Generally entered from annual agent summary
A42: Rent - Collected by Owner/s | C42: 0 | F42: This assists accountant to address agent fees inconsistencies etc
A43: Bond retained (damage) NOT bond received for new tenant | C43: 0 | F43: Bond retained for damage etc only. Also show repair costs below.
A44: Insurance claim for lost rent / damage etc | C44: 0 | F44: This is assessable when received. Also sho repair costs. If insurer rectified damage then ignore issue
A45: Letting or other fee paid by tenant (ie water) | C45: 0 | F45: All tenant contributions to costs are to be shown here
A46: Tenant contribution for repairs / Loss | C46: 0 | F46: Ensure the repairs etc is also shown below.
A47: Total Income | C47: =SUM(C41:C46) -> 21820.36
A51: Expenses
A52: Advertising for tenants | C52: 0
A53: Asbestos removal costs | C53: 0 | F53: A specific deduction for removing asbestos may be available
A54: Body Corp / Strata - Ordinary levies | C54: 0 | F54: Do not include strata adjustments on new property acquisition. Include below 2 lines below
A55: Body Corp / Strata - Special levies | C55: 0 | D55: NOT DEDUCTIBLE…………………. | F55: Special levies may increase QS depreciation if amended by QS after completion of works
A56: Body Corp / Strata - For newly acquired property (only) | C56: 0 | F56: New acquisition only. Include strata levy settlement adjustment from lawyers settlement here
A57: Borrowing Expenses - Annual Loyalty / Package Fee | C57: 0 | F57: Show the % of annual fee relating to discounts for this property v's others
A58: Borrowing Expenses - Monthly Fees | C58: 0 | F58: Bank lender monthly fees etc eg $8pm x 12= $96
A59: Break costs (Fixed to variable loan) | C59: 0 | F59: Deductible unless broken to dispose of property. Discuss
A60: Cleaning, waste and rubbish removal | C60: 0 | F60: Not for initial tenancy. Between or after tenancy
A61: Council rates | C61: 2624.3 | F61: Do not include rates adjustments on new acquisitions here. Include next row
A62: Council rates - For newly acquired property (only) | C62: 0 | F62: New acquisition only. Include rates adjustment from lawyers settlement here
A63: Depreciation from Quantity Surveyor report | C63: 10252 | F63: Do not include capital allowances (Div 43). Include that below.
A64: Gardens lawns and yard maintenance | C64: 0 | F64: Can include tree removal etc if existing tenancy
A65: Insurance - Building | C65: 1835.51 | F65: Include premiums paid in period. Do not adjust for period of time
A66: Insurance - Contents | C66: 0 | F66: Include premiums paid in period. Do not adjust for period of time
A67: Insurance - Landlord policy | C67: 300.21 | F67: Include premiums paid in period. Do not adjust for period of time
... A74: Pest Control | C74: 0 | F74: Do NOT show initial P&B or initial repairs here
A75: Property Agent (incl GST) incl letting fees | C75: =1855+120+197.5 -> 2172.5
A76: Repairs & Maintenance - Before tenant | C76: 0 | D76: NOT DEDUCTIBLE…………………. | F76: Initial repairs are non-deductible. May be depreciable
A77: Repairs & Maintenance incl Tenant damage / wear | C77: 2448.7 | F77: Do NOT include depreciable items replaced here
A78: Quantity Surveyor Report Fee | C78: 0 | F78: Only show cost if a new report was obtained and paid this tax year
A79: Stationery, Phone, Post etc | C79: 100
A80: Travel - Any purpose, any reason = Non-deductible | D80: NOT DEDUCTIBLE…………………. | F80: Travel cannot be included in capital costs, deductions or repair costs
A81: Water | C81: 119 | F81: Include costs paid. If tenant reimbursed include that as income. Incl QLD fee for reading
A82: Water - For newly acquired property (only) | C82: 0 | F82: New acquisition only. Include upwards water adjustment from lawyers settlement here
A83: Sundry Costs | C83: 0 | F83: Details :
A84: Total Expenses | C84: =SUM(C52:C83) -> 37086.19
A86: Estimated Profit (Loss) before tax considerations | C86: =(C47-C84) -> -15265.83
A89: Borrowing Expenses
A91: Refinance Expenses (this financial year). For new acquisitions please provide lender information instead
A92: Did you refinance a former loan ? | B92: No
A93: Is the loan amount the same as previously | B93: Yes | C93: Answers No may be incorrect unless new funds were to improve or renovate.
A94: Total loan fees incurred to refinance this | B94: $ | C94: (If the refinance was to buy a new property the costs may need be applied to that new property instead of this property)
A95: Was there a break cost for THIS loan | B95: $ | C95: Eg Break a fixed loan
A97: New finance fees - For a new property generally. If new borrowing for new IP using equity include on THAT property. Not here
A98: Total borrowing expenses | B98: $ | C98: Include ALL bank fees for the loan incl appn, broker, valuation, legals by bank and LMI. Provide accountant with lender letter
A99: Is loan term greater than 5 years ? | B99: Yes | C99: Accountant will calculate a deduction based on loan term OR 60 months (shorter) and include a schedule in return.
C100: Do NOT include stamp duty or property settlement legal costs
A102: Borrowing Expenses from prior year/s (E.g. Lenders Mortgage Insurance)
A103: What was the loan start date | B103: 25/1/2016
A104: What was the total borrowing expense at that time | B104: 5640
A107: New Costs to add to Depreciation and Cap Allowances
A108: Did you incur any costs for a NON-DEDUCTIBLE item costing $300+ or a improvement, renovations etc (not a repair) ?
A109: Add further details or a summary if required. If any costs are included on a QS report do not include them to avoid duplication
A110: Please show the installed cost. Eg Oven $800 + $300 Install = $1100
A111: Advise details: Indicate if item is second hand please
A113: What was cost for | B113: Amount | C113: Date completed
B114: $
B115: $
B116: $
B117: $
B118: $
B119: $
B120: $
A122: Terms & Conditions: © Consulting By PK - All rights reserved. Do not share, copy, reproduce or sell any part of this document unless you have written permission from Consulting By PK. All infringements will be prosecuted. If you are the personal owner of the Consulting By PK End User License then you may use it for your own use but not for any other purpose. Disclaimer: The opinions expressed in all material published by Consulting By PK are not to be construed as financial or investment advice nor should be relied upon for any investment activities. Consulting By PK strongly recommends that you perform your own independent research and/or seek your own legal advice before making any financial decisions. Contents of this message are of general nature only and should not be relied upon solely when making an investment decision. Consulting By PK nor any of its directors, associates, staff, or associated companies bear any liability from any actions derived from in this document. One should always seek third party investment information from relevant parties such as legal, finance, and accountancy enquiries.

Sheet Property 4
A1: Property 4
A3: Estimated Cashflow before tax considerations | B3: =C86+C63 -> -5013.83
A4: Approximate refund due from ATO | B4: =-C86*C4 -> 5648.3571 | C4: 0.37 | D4: < Insert your tax rate
A5: Estimated Cashflow after tax considerations | B5: =B3+B4 -> 634.5271
A8: Address
F9: Guidance Notes
A11: Complete this table in full please :
A12: Date property acquired : | E12: 42394 | F12: Date settled
A13: Do you have a Quantity Surveyor Report (Depreciation Schedule)? | E13: Yes | F13: Ensure accountant is provided with this. Upload ONCE when new OR replaced
A15: If a new IP but not acquired this year, was this a former home ? | E15: Please answer
A16: If so, do you know its market value on the date it first earned rent ? | E16: Please answer | F16: This can affect CGT costbase
A18: If acquired prior to this tax year - Was property refinanced this year ? | E18: No | F18: Borrowing expenses may be impacted. Refer below
A19: If refinanced this year was the loan increased ? | E19: Please answer | F19: If so, the new loan may be deductible against the new IP or new investment. Or Non-deductible. Info reqd
A21: Is this property NRAS ? | E21: No
A22: If it is, do you have the certificate for annual incentives yet ? | E22: No
A23: What is the State Incentive Amount ? | E23: $
A24: What is the Commonwealth Tax Credit Amount ? | E24: $
A26: Since the start of the financial year have you or others ever resided within this property rent free ? | E26: No
A28: Period available to rent in Financial Year | B28: Start | C28: End | F28: Explain if not available for the whole period, Change dates please
A29: Start | B29: 43282 | C29: 43646
A31: Ownership of property | B31: % | F31: Full name/s of all owners and their % share of title is essential
A32: Name of Owner 1 | B32: 1
A33: Name of Owner 2 | B33: 0
A34: Name of Owner 3 | B34: 0
A35: Name of Owner 4 | B35: 0
B36: =SUM(B32:B35) -> 1 | F36: Must add to 100%
A39: Income and Expenses Summary for this property
A41: Rent - Collected by Agent/s | C41: 21820.36 | F41: Generally entered from annual agent summary
A42: Rent - Collected by Owner/s | C42: 0 | F42: This assists accountant to address agent fees inconsistencies etc
A43: Bond retained (damage) NOT bond received for new tenant | C43: 0 | F43: Bond retained for damage etc only. Also show repair costs below.
A44: Insurance claim for lost rent / damage etc | C44: 0 | F44: This is assessable when received. Also sho repair costs. If insurer rectified damage then ignore issue
A45: Letting or other fee paid by tenant (ie water) | C45: 0 | F45: All tenant contributions to costs are to be shown here
A46: Tenant contribution for repairs / Loss | C46: 0 | F46: Ensure the repairs etc is also shown below.
A47: Total Income | C47: =SUM(C41:C46) -> 21820.36
A51: Expenses
A52: Advertising for tenants | C52: 0
A53: Asbestos removal costs | C53: 0 | F53: A specific deduction for removing asbestos may be available
A54: Body Corp / Strata - Ordinary levies | C54: 0 | F54: Do not include strata adjustments on new property acquisition. Include below 2 lines below
A55: Body Corp / Strata - Special levies | C55: 0 | D55: NOT DEDUCTIBLE…………………. | F55: Special levies may increase QS depreciation if amended by QS after completion of works
A56: Body Corp / Strata - For newly acquired property (only) | C56: 0 | F56: New acquisition only. Include strata levy settlement adjustment from lawyers settlement here
A57: Borrowing Expenses - Annual Loyalty / Package Fee | C57: 0 | F57: Show the % of annual fee relating to discounts for this property v's others
A58: Borrowing Expenses - Monthly Fees | C58: 0 | F58: Bank lender monthly fees etc eg $8pm x 12= $96
A59: Break costs (Fixed to variable loan) | C59: 0 | F59: Deductible unless broken to dispose of property. Discuss
A60: Cleaning, waste and rubbish removal | C60: 0 | F60: Not for initial tenancy. Between or after tenancy
A61: Council rates | C61: 2624.3 | F61: Do not include rates adjustments on new acquisitions here. Include next row
A62: Council rates - For newly acquired property (only) | C62: 0 | F62: New acquisition only. Include rates adjustment from lawyers settlement here
A63: Depreciation from Quantity Surveyor report | C63: 10252 | F63: Do not include capital allowances (Div 43). Include that below.
A64: Gardens lawns and yard maintenance | C64: 0 | F64: Can include tree removal etc if existing tenancy
A65: Insurance - Building | C65: 1835.51 | F65: Include premiums paid in period. Do not adjust for period of time
A66: Insurance - Contents | C66: 0 | F66: Include premiums paid in period. Do not adjust for period of time
A67: Insurance - Landlord policy | C67: 300.21 | F67: Include premiums paid in period. Do not adjust for period of time
... A74: Pest Control | C74: 0 | F74: Do NOT show initial P&B or initial repairs here
A75: Property Agent (incl GST) incl letting fees | C75: =1855+120+197.5 -> 2172.5
A76: Repairs & Maintenance - Before tenant | C76: 0 | D76: NOT DEDUCTIBLE…………………. | F76: Initial repairs are non-deductible. May be depreciable
A77: Repairs & Maintenance incl Tenant damage / wear | C77: 2448.7 | F77: Do NOT include depreciable items replaced here
A78: Quantity Surveyor Report Fee | C78: 0 | F78: Only show cost if a new report was obtained and paid this tax year
A79: Stationery, Phone, Post etc | C79: 100
A80: Travel - Any purpose, any reason = Non-deductible | D80: NOT DEDUCTIBLE…………………. | F80: Travel cannot be included in capital costs, deductions or repair costs
A81: Water | C81: 119 | F81: Include costs paid. If tenant reimbursed include that as income. Incl QLD fee for reading
A82: Water - For newly acquired property (only) | C82: 0 | F82: New acquisition only. Include upwards water adjustment from lawyers settlement here
A83: Sundry Costs | C83: 0 | F83: Details :
A84: Total Expenses | C84: =SUM(C52:C83) -> 37086.19
A86: Estimated Profit (Loss) before tax considerations | C86: =(C47-C84) -> -15265.83
A89: Borrowing Expenses
A91: Refinance Expenses (this financial year). For new acquisitions please provide lender information instead
A92: Did you refinance a former loan ? | B92: No
A93: Is the loan amount the same as previously | B93: Yes | C93: Answers No may be incorrect unless new funds were to improve or renovate.
A94: Total loan fees incurred to refinance this | B94: $ | C94: (If the refinance was to buy a new property the costs may need be applied to that new property instead of this property)
A95: Was there a break cost for THIS loan | B95: $ | C95: Eg Break a fixed loan
A97: New finance fees - For a new property generally. If new borrowing for new IP using equity include on THAT property. Not here
A98: Total borrowing expenses | B98: $ | C98: Include ALL bank fees for the loan incl appn, broker, valuation, legals by bank and LMI. Provide accountant with lender letter
A99: Is loan term greater than 5 years ? | B99: Yes | C99: Accountant will calculate a deduction based on loan term OR 60 months (shorter) and include a schedule in return.
C100: Do NOT include stamp duty or property settlement legal costs
A102: Borrowing Expenses from prior year/s (E.g. Lenders Mortgage Insurance)
A103: What was the loan start date | B103: 25/1/2016
A104: What was the total borrowing expense at that time | B104: 5640
A107: New Costs to add to Depreciation and Cap Allowances
A108: Did you incur any costs for a NON-DEDUCTIBLE item costing $300+ or a improvement, renovations etc (not a repair) ?
A109: Add further details or a summary if required. If any costs are included on a QS report do not include them to avoid duplication
A110: Please show the installed cost. Eg Oven $800 + $300 Install = $1100
A111: Advise details: Indicate if item is second hand please
A113: What was cost for | B113: Amount | C113: Date completed
B114: $
B115: $
B116: $
B117: $
B118: $
B119: $
B120: $
A122: Terms & Conditions: © Consulting By PK - All rights reserved. Do not share, copy, reproduce or sell any part of this document unless you have written permission from Consulting By PK. All infringements will be prosecuted. If you are the personal owner of the Consulting By PK End User License then you may use it for your own use but not for any other purpose. Disclaimer: The opinions expressed in all material published by Consulting By PK are not to be construed as financial or investment advice nor should be relied upon for any investment activities. Consulting By PK strongly recommends that you perform your own independent research and/or seek your own legal advice before making any financial decisions. Contents of this message are of general nature only and should not be relied upon solely when making an investment decision. Consulting By PK nor any of its directors, associates, staff, or associated companies bear any liability from any actions derived from in this document. One should always seek third party investment information from relevant parties such as legal, finance, and accountancy enquiries.

Sheet Property 5
A1: Property 5
A3: Estimated Cashflow before tax considerations | B3: =C86+C63 -> -5013.83
A4: Approximate refund due from ATO | B4: =-C86*C4 -> 5648.3571 | C4: 0.37 | D4: < Insert your tax rate
A5: Estimated Cashflow after tax considerations | B5: =B3+B4 -> 634.5271
A8: Address
F9: Guidance Notes
A11: Complete this table in full please :
A12: Date property acquired : | E12: 42394 | F12: Date settled
A13: Do you have a Quantity Surveyor Report (Depreciation Schedule)? | E13: Yes | F13: Ensure accountant is provided with this. Upload ONCE when new OR replaced
A15: If a new IP but not acquired this year, was this a former home ? | E15: Please answer
A16: If so, do you know its market value on the date it first earned rent ? | E16: Please answer | F16: This can affect CGT costbase
A18: If acquired prior to this tax year - Was property refinanced this year ? | E18: No | F18: Borrowing expenses may be impacted. Refer below
A19: If refinanced this year was the loan increased ? | E19: Please answer | F19: If so, the new loan may be deductible against the new IP or new investment. Or Non-deductible. Info reqd
A21: Is this property NRAS ? | E21: No
A22: If it is, do you have the certificate for annual incentives yet ? | E22: No
A23: What is the State Incentive Amount ? | E23: $
A24: What is the Commonwealth Tax Credit Amount ? | E24: $
A26: Since the start of the financial year have you or others ever resided within this property rent free ? | E26: No
A28: Period available to rent in Financial Year | B28: Start | C28: End | F28: Explain if not available for the whole period, Change dates please
A29: Start | B29: 43282 | C29: 43646
A31: Ownership of property | B31: % | F31: Full name/s of all owners and their % share of title is essential
A32: Name of Owner 1 | B32: 1
A33: Name of Owner 2 | B33: 0
A34: Name of Owner 3 | B34: 0
A35: Name of Owner 4 | B35: 0
B36: =SUM(B32:B35) -> 1 | F36: Must add to 100%
A39: Income and Expenses Summary for this property
A41: Rent - Collected by Agent/s | C41: 21820.36 | F41: Generally entered from annual agent summary
A42: Rent - Collected by Owner/s | C42: 0 | F42: This assists accountant to address agent fees inconsistencies etc
A43: Bond retained (damage) NOT bond received for new tenant | C43: 0 | F43: Bond retained for damage etc only. Also show repair costs below.
A44: Insurance claim for lost rent / damage etc | C44: 0 | F44: This is assessable when received. Also sho repair costs. If insurer rectified damage then ignore issue
A45: Letting or other fee paid by tenant (ie water) | C45: 0 | F45: All tenant contributions to costs are to be shown here
A46: Tenant contribution for repairs / Loss | C46: 0 | F46: Ensure the repairs etc is also shown below.
A47: Total Income | C47: =SUM(C41:C46) -> 21820.36
A51: Expenses
A52: Advertising for tenants | C52: 0
A53: Asbestos removal costs | C53: 0 | F53: A specific deduction for removing asbestos may be available
A54: Body Corp / Strata - Ordinary levies | C54: 0 | F54: Do not include strata adjustments on new property acquisition. Include below 2 lines below
A55: Body Corp / Strata - Special levies | C55: 0 | D55: NOT DEDUCTIBLE…………………. | F55: Special levies may increase QS depreciation if amended by QS after completion of works
A56: Body Corp / Strata - For newly acquired property (only) | C56: 0 | F56: New acquisition only. Include strata levy settlement adjustment from lawyers settlement here
A57: Borrowing Expenses - Annual Loyalty / Package Fee | C57: 0 | F57: Show the % of annual fee relating to discounts for this property v's others
A58: Borrowing Expenses - Monthly Fees | C58: 0 | F58: Bank lender monthly fees etc eg $8pm x 12= $96
A59: Break costs (Fixed to variable loan) | C59: 0 | F59: Deductible unless broken to dispose of property. Discuss
A60: Cleaning, waste and rubbish removal | C60: 0 | F60: Not for initial tenancy. Between or after tenancy
A61: Council rates | C61: 2624.3 | F61: Do not include rates adjustments on new acquisitions here. Include next row
A62: Council rates - For newly acquired property (only) | C62: 0 | F62: New acquisition only. Include rates adjustment from lawyers settlement here
A63: Depreciation from Quantity Surveyor report | C63: 10252 | F63: Do not include capital allowances (Div 43). Include that below.
A64: Gardens lawns and yard maintenance | C64: 0 | F64: Can include tree removal etc if existing tenancy
A65: Insurance - Building | C65: 1835.51 | F65: Include premiums paid in period. Do not adjust for period of time
A66: Insurance - Contents | C66: 0 | F66: Include premiums paid in period. Do not adjust for period of time
A67: Insurance - Landlord policy | C67: 300.21 | F67: Include premiums paid in period. Do not adjust for period of time
... A74: Pest Control | C74: 0 | F74: Do NOT show initial P&B or initial repairs here
A75: Property Agent (incl GST) incl letting fees | C75: =1855+120+197.5 -> 2172.5
A76: Repairs & Maintenance - Before tenant | C76: 0 | D76: NOT DEDUCTIBLE…………………. | F76: Initial repairs are non-deductible. May be depreciable
A77: Repairs & Maintenance incl Tenant damage / wear | C77: 2448.7 | F77: Do NOT include depreciable items replaced here
A78: Quantity Surveyor Report Fee | C78: 0 | F78: Only show cost if a new report was obtained and paid this tax year
A79: Stationery, Phone, Post etc | C79: 100
A80: Travel - Any purpose, any reason = Non-deductible | D80: NOT DEDUCTIBLE…………………. | F80: Travel cannot be included in capital costs, deductions or repair costs
A81: Water | C81: 119 | F81: Include costs paid. If tenant reimbursed include that as income. Incl QLD fee for reading
A82: Water - For newly acquired property (only) | C82: 0 | F82: New acquisition only. Include upwards water adjustment from lawyers settlement here
A83: Sundry Costs | C83: 0 | F83: Details :
A84: Total Expenses | C84: =SUM(C52:C83) -> 37086.19
A86: Estimated Profit (Loss) before tax considerations | C86: =(C47-C84) -> -15265.83
A89: Borrowing Expenses
A91: Refinance Expenses (this financial year). For new acquisitions please provide lender information instead
A92: Did you refinance a former loan ? | B92: No
A93: Is the loan amount the same as previously | B93: Yes | C93: Answers No may be incorrect unless new funds were to improve or renovate.
A94: Total loan fees incurred to refinance this | B94: $ | C94: (If the refinance was to buy a new property the costs may need be applied to that new property instead of this property)
A95: Was there a break cost for THIS loan | B95: $ | C95: Eg Break a fixed loan
A97: New finance fees - For a new property generally. If new borrowing for new IP using equity include on THAT property. Not here
A98: Total borrowing expenses | B98: $ | C98: Include ALL bank fees for the loan incl appn, broker, valuation, legals by bank and LMI. Provide accountant with lender letter
A99: Is loan term greater than 5 years ? | B99: Yes | C99: Accountant will calculate a deduction based on loan term OR 60 months (shorter) and include a schedule in return.
C100: Do NOT include stamp duty or property settlement legal costs
A102: Borrowing Expenses from prior year/s (E.g. Lenders Mortgage Insurance)
A103: What was the loan start date | B103: 25/1/2016
A104: What was the total borrowing expense at that time | B104: 5640
A107: New Costs to add to Depreciation and Cap Allowances
A108: Did you incur any costs for a NON-DEDUCTIBLE item costing $300+ or a improvement, renovations etc (not a repair) ?
A109: Add further details or a summary if required. If any costs are included on a QS report do not include them to avoid duplication
A110: Please show the installed cost. Eg Oven $800 + $300 Install = $1100
A111: Advise details: Indicate if item is second hand please
A113: What was cost for | B113: Amount | C113: Date completed
B114: $
B115: $
B116: $
B117: $
B118: $
B119: $
B120: $
A122: Terms & Conditions: © Consulting By PK - All rights reserved. Do not share, copy, reproduce or sell any part of this document unless you have written permission from Consulting By PK. All infringements will be prosecuted. If you are the personal owner of the Consulting By PK End User License then you may use it for your own use but not for any other purpose. Disclaimer: The opinions expressed in all material published by Consulting By PK are not to be construed as financial or investment advice nor should be relied upon for any investment activities. Consulting By PK strongly recommends that you perform your own independent research and/or seek your own legal advice before making any financial decisions. Contents of this message are of general nature only and should not be relied upon solely when making an investment decision. Consulting By PK nor any of its directors, associates, staff, or associated companies bear any liability from any actions derived from in this document. One should always seek third party investment information from relevant parties such as legal, finance, and accountancy enquiries.

Sheet Property 6
A1: Property 6
A3: Estimated Cashflow before tax considerations | B3: =C86+C63 -> -5013.83
A4: Approximate refund due from ATO | B4: =-C86*C4 -> 5648.3571 | C4: 0.37 | D4: < Insert your tax rate
A5: Estimated Cashflow after tax considerations | B5: =B3+B4 -> 634.5271
A8: Address
F9: Guidance Notes
A11: Complete this table in full please :
A12: Date property acquired : | E12: 42394 | F12: Date settled
A13: Do you have a Quantity Surveyor Report (Depreciation Schedule)? | E13: Yes | F13: Ensure accountant is provided with this. Upload ONCE when new OR replaced
A15: If a new IP but not acquired this year, was this a former home ? | E15: Please answer
A16: If so, do you know its market value on the date it first earned rent ? | E16: Please answer | F16: This can affect CGT costbase
A18: If acquired prior to this tax year - Was property refinanced this year ? | E18: No | F18: Borrowing expenses may be impacted. Refer below
A19: If refinanced this year was the loan increased ? | E19: Please answer | F19: If so, the new loan may be deductible against the new IP or new investment. Or Non-deductible. Info reqd
A21: Is this property NRAS ? | E21: No
A22: If it is, do you have the certificate for annual incentives yet ? | E22: No
A23: What is the State Incentive Amount ? | E23: $
A24: What is the Commonwealth Tax Credit Amount ? | E24: $
A26: Since the start of the financial year have you or others ever resided within this property rent free ? | E26: No
A28: Period available to rent in Financial Year | B28: Start | C28: End | F28: Explain if not available for the whole period, Change dates please
A29: Start | B29: 43282 | C29: 43646
A31: Ownership of property | B31: % | F31: Full name/s of all owners and their % share of title is essential
A32: Name of Owner 1 | B32: 1
A33: Name of Owner 2 | B33: 0
A34: Name of Owner 3 | B34: 0
A35: Name of Owner 4 | B35: 0
B36: =SUM(B32:B35) -> 1 | F36: Must add to 100%
A39: Income and Expenses Summary for this property
A41: Rent - Collected by Agent/s | C41: 21820.36 | F41: Generally entered from annual agent summary
A42: Rent - Collected by Owner/s | C42: 0 | F42: This assists accountant to address agent fees inconsistencies etc
A43: Bond retained (damage) NOT bond received for new tenant | C43: 0 | F43: Bond retained for damage etc only. Also show repair costs below.
A44: Insurance claim for lost rent / damage etc | C44: 0 | F44: This is assessable when received. Also sho repair costs. If insurer rectified damage then ignore issue
A45: Letting or other fee paid by tenant (ie water) | C45: 0 | F45: All tenant contributions to costs are to be shown here
A46: Tenant contribution for repairs / Loss | C46: 0 | F46: Ensure the repairs etc is also shown below.
A47: Total Income | C47: =SUM(C41:C46) -> 21820.36
A51: Expenses
A52: Advertising for tenants | C52: 0
A53: Asbestos removal costs | C53: 0 | F53: A specific deduction for removing asbestos may be available
A54: Body Corp / Strata - Ordinary levies | C54: 0 | F54: Do not include strata adjustments on new property acquisition. Include below 2 lines below
A55: Body Corp / Strata - Special levies | C55: 0 | D55: NOT DEDUCTIBLE…………………. | F55: Special levies may increase QS depreciation if amended by QS after completion of works
A56: Body Corp / Strata - For newly acquired property (only) | C56: 0 | F56: New acquisition only. Include strata levy settlement adjustment from lawyers settlement here
A57: Borrowing Expenses - Annual Loyalty / Package Fee | C57: 0 | F57: Show the % of annual fee relating to discounts for this property v's others
A58: Borrowing Expenses - Monthly Fees | C58: 0 | F58: Bank lender monthly fees etc eg $8pm x 12= $96
A59: Break costs (Fixed to variable loan) | C59: 0 | F59: Deductible unless broken to dispose of property. Discuss
A60: Cleaning, waste and rubbish removal | C60: 0 | F60: Not for initial tenancy. Between or after tenancy
A61: Council rates | C61: 2624.3 | F61: Do not include rates adjustments on new acquisitions here. Include next row
A62: Council rates - For newly acquired property (only) | C62: 0 | F62: New acquisition only. Include rates adjustment from lawyers settlement here
A63: Depreciation from Quantity Surveyor report | C63: 10252 | F63: Do not include capital allowances (Div 43). Include that below.
A64: Gardens lawns and yard maintenance | C64: 0 | F64: Can include tree removal etc if existing tenancy
A65: Insurance - Building | C65: 1835.51 | F65: Include premiums paid in period. Do not adjust for period of time
A66: Insurance - Contents | C66: 0 | F66: Include premiums paid in period. Do not adjust for period of time
A67: Insurance - Landlord policy | C67: 300.21 | F67: Include premiums paid in period. Do not adjust for period of time
... A74: Pest Control | C74: 0 | F74: Do NOT show initial P&B or initial repairs here
A75: Property Agent (incl GST) incl letting fees | C75: =1855+120+197.5 -> 2172.5
A76: Repairs & Maintenance - Before tenant | C76: 0 | D76: NOT DEDUCTIBLE…………………. | F76: Initial repairs are non-deductible. May be depreciable
A77: Repairs & Maintenance incl Tenant damage / wear | C77: 2448.7 | F77: Do NOT include depreciable items replaced here
A78: Quantity Surveyor Report Fee | C78: 0 | F78: Only show cost if a new report was obtained and paid this tax year
A79: Stationery, Phone, Post etc | C79: 100
A80: Travel - Any purpose, any reason = Non-deductible | D80: NOT DEDUCTIBLE…………………. | F80: Travel cannot be included in capital costs, deductions or repair costs
A81: Water | C81: 119 | F81: Include costs paid. If tenant reimbursed include that as income. Incl QLD fee for reading
A82: Water - For newly acquired property (only) | C82: 0 | F82: New acquisition only. Include upwards water adjustment from lawyers settlement here
A83: Sundry Costs | C83: 0 | F83: Details :
A84: Total Expenses | C84: =SUM(C52:C83) -> 37086.19
A86: Estimated Profit (Loss) before tax considerations | C86: =(C47-C84) -> -15265.83
A89: Borrowing Expenses
A91: Refinance Expenses (this financial year). For new acquisitions please provide lender information instead
A92: Did you refinance a former loan ? | B92: No
A93: Is the loan amount the same as previously | B93: Yes | C93: Answers No may be incorrect unless new funds were to improve or renovate.
A94: Total loan fees incurred to refinance this | B94: $ | C94: (If the refinance was to buy a new property the costs may need be applied to that new property instead of this property)
A95: Was there a break cost for THIS loan | B95: $ | C95: Eg Break a fixed loan
A97: New finance fees - For a new property generally. If new borrowing for new IP using equity include on THAT property. Not here
A98: Total borrowing expenses | B98: $ | C98: Include ALL bank fees for the loan incl appn, broker, valuation, legals by bank and LMI. Provide accountant with lender letter
A99: Is loan term greater than 5 years ? | B99: Yes | C99: Accountant will calculate a deduction based on loan term OR 60 months (shorter) and include a schedule in return.
C100: Do NOT include stamp duty or property settlement legal costs
A102: Borrowing Expenses from prior year/s (E.g. Lenders Mortgage Insurance)
A103: What was the loan start date | B103: 25/1/2016
A104: What was the total borrowing expense at that time | B104: 5640
A107: New Costs to add to Depreciation and Cap Allowances
A108: Did you incur any costs for a NON-DEDUCTIBLE item costing $300+ or a improvement, renovations etc (not a repair) ?
A109: Add further details or a summary if required. If any costs are included on a QS report do not include them to avoid duplication
A110: Please show the installed cost. Eg Oven $800 + $300 Install = $1100
A111: Advise details: Indicate if item is second hand please
A113: What was cost for | B113: Amount | C113: Date completed
B114: $
B115: $
B116: $
B117: $
B118: $
B119: $
B120: $
A122: Terms & Conditions: © Consulting By PK - All rights reserved. Do not share, copy, reproduce or sell any part of this document unless you have written permission from Consulting By PK. All infringements will be prosecuted. If you are the personal owner of the Consulting By PK End User License then you may use it for your own use but not for any other purpose. Disclaimer: The opinions expressed in all material published by Consulting By PK are not to be construed as financial or investment advice nor should be relied upon for any investment activities. Consulting By PK strongly recommends that you perform your own independent research and/or seek your own legal advice before making any financial decisions. Contents of this message are of general nature only and should not be relied upon solely when making an investment decision. Consulting By PK nor any of its directors, associates, staff, or associated companies bear any liability from any actions derived from in this document. One should always seek third party investment information from relevant parties such as legal, finance, and accountancy enquiries.

Sheet Property 7
A1: Property 7
A3: Estimated Cashflow before tax considerations | B3: =C86+C63 -> -5013.83
A4: Approximate refund due from ATO | B4: =-C86*C4 -> 5648.3571 | C4: 0.37 | D4: < Insert your tax rate
A5: Estimated Cashflow after tax considerations | B5: =B3+B4 -> 634.5271
A8: Address
F9: Guidance Notes
A11: Complete this table in full please :
A12: Date property acquired : | E12: 42394 | F12: Date settled
A13: Do you have a Quantity Surveyor Report (Depreciation Schedule)? | E13: Yes | F13: Ensure accountant is provided with this. Upload ONCE when new OR replaced
A15: If a new IP but not acquired this year, was this a former home ? | E15: Please answer
A16: If so, do you know its market value on the date it first earned rent ? | E16: Please answer | F16: This can affect CGT costbase
A18: If acquired prior to this tax year - Was property refinanced this year ? | E18: No | F18: Borrowing expenses may be impacted. Refer below
A19: If refinanced this year was the loan increased ? | E19: Please answer | F19: If so, the new loan may be deductible against the new IP or new investment. Or Non-deductible. Info reqd
A21: Is this property NRAS ? | E21: No
A22: If it is, do you have the certificate for annual incentives yet ? | E22: No
A23: What is the State Incentive Amount ? | E23: $
A24: What is the Commonwealth Tax Credit Amount ? | E24: $
A26: Since the start of the financial year have you or others ever resided within this property rent free ? | E26: No
A28: Period available to rent in Financial Year | B28: Start | C28: End | F28: Explain if not available for the whole period, Change dates please
A29: Start | B29: 43282 | C29: 43646
A31: Ownership of property | B31: % | F31: Full name/s of all owners and their % share of title is essential
A32: Name of Owner 1 | B32: 1
A33: Name of Owner 2 | B33: 0
A34: Name of Owner 3 | B34: 0
A35: Name of Owner 4 | B35: 0
B36: =SUM(B32:B35) -> 1 | F36: Must add to 100%
A39: Income and Expenses Summary for this property
A41: Rent - Collected by Agent/s | C41: 21820.36 | F41: Generally entered from annual agent summary
A42: Rent - Collected by Owner/s | C42: 0 | F42: This assists accountant to address agent fees inconsistencies etc
A43: Bond retained (damage) NOT bond received for new tenant | C43: 0 | F43: Bond retained for damage etc only. Also show repair costs below.
A44: Insurance claim for lost rent / damage etc | C44: 0 | F44: This is assessable when received. Also sho repair costs. If insurer rectified damage then ignore issue
A45: Letting or other fee paid by tenant (ie water) | C45: 0 | F45: All tenant contributions to costs are to be shown here
A46: Tenant contribution for repairs / Loss | C46: 0 | F46: Ensure the repairs etc is also shown below.
A47: Total Income | C47: =SUM(C41:C46) -> 21820.36
A51: Expenses
A52: Advertising for tenants | C52: 0
A53: Asbestos removal costs | C53: 0 | F53: A specific deduction for removing asbestos may be available
A54: Body Corp / Strata - Ordinary levies | C54: 0 | F54: Do not include strata adjustments on new property acquisition. Include below 2 lines below
A55: Body Corp / Strata - Special levies | C55: 0 | D55: NOT DEDUCTIBLE…………………. | F55: Special levies may increase QS depreciation if amended by QS after completion of works
A56: Body Corp / Strata - For newly acquired property (only) | C56: 0 | F56: New acquisition only. Include strata levy settlement adjustment from lawyers settlement here
A57: Borrowing Expenses - Annual Loyalty / Package Fee | C57: 0 | F57: Show the % of annual fee relating to discounts for this property v's others
A58: Borrowing Expenses - Monthly Fees | C58: 0 | F58: Bank lender monthly fees etc eg $8pm x 12= $96
A59: Break costs (Fixed to variable loan) | C59: 0 | F59: Deductible unless broken to dispose of property. Discuss
A60: Cleaning, waste and rubbish removal | C60: 0 | F60: Not for initial tenancy. Between or after tenancy
A61: Council rates | C61: 2624.3 | F61: Do not include rates adjustments on new acquisitions here. Include next row
A62: Council rates - For newly acquired property (only) | C62: 0 | F62: New acquisition only. Include rates adjustment from lawyers settlement here
A63: Depreciation from Quantity Surveyor report | C63: 10252 | F63: Do not include capital allowances (Div 43). Include that below.
A64: Gardens lawns and yard maintenance | C64: 0 | F64: Can include tree removal etc if existing tenancy
A65: Insurance - Building | C65: 1835.51 | F65: Include premiums paid in period. Do not adjust for period of time
A66: Insurance - Contents | C66: 0 | F66: Include premiums paid in period. Do not adjust for period of time
A67: Insurance - Landlord policy | C67: 300.21 | F67: Include premiums paid in period. Do not adjust for period of time
... A74: Pest Control | C74: 0 | F74: Do NOT show initial P&B or initial repairs here
A75: Property Agent (incl GST) incl letting fees | C75: =1855+120+197.5 -> 2172.5
A76: Repairs & Maintenance - Before tenant | C76: 0 | D76: NOT DEDUCTIBLE…………………. | F76: Initial repairs are non-deductible. May be depreciable
A77: Repairs & Maintenance incl Tenant damage / wear | C77: 2448.7 | F77: Do NOT include depreciable items replaced here
A78: Quantity Surveyor Report Fee | C78: 0 | F78: Only show cost if a new report was obtained and paid this tax year
A79: Stationery, Phone, Post etc | C79: 100
A80: Travel - Any purpose, any reason = Non-deductible | D80: NOT DEDUCTIBLE…………………. | F80: Travel cannot be included in capital costs, deductions or repair costs
A81: Water | C81: 119 | F81: Include costs paid. If tenant reimbursed include that as income. Incl QLD fee for reading
A82: Water - For newly acquired property (only) | C82: 0 | F82: New acquisition only. Include upwards water adjustment from lawyers settlement here
A83: Sundry Costs | C83: 0 | F83: Details :
A84: Total Expenses | C84: =SUM(C52:C83) -> 37086.19
A86: Estimated Profit (Loss) before tax considerations | C86: =(C47-C84) -> -15265.83
A89: Borrowing Expenses
A91: Refinance Expenses (this financial year). For new acquisitions please provide lender information instead
A92: Did you refinance a former loan ? | B92: No
A93: Is the loan amount the same as previously | B93: Yes | C93: Answers No may be incorrect unless new funds were to improve or renovate.
A94: Total loan fees incurred to refinance this | B94: $ | C94: (If the refinance was to buy a new property the costs may need be applied to that new property instead of this property)
A95: Was there a break cost for THIS loan | B95: $ | C95: Eg Break a fixed loan
A97: New finance fees - For a new property generally. If new borrowing for new IP using equity include on THAT property. Not here
A98: Total borrowing expenses | B98: $ | C98: Include ALL bank fees for the loan incl appn, broker, valuation, legals by bank and LMI. Provide accountant with lender letter
A99: Is loan term greater than 5 years ? | B99: Yes | C99: Accountant will calculate a deduction based on loan term OR 60 months (shorter) and include a schedule in return.
C100: Do NOT include stamp duty or property settlement legal costs
A102: Borrowing Expenses from prior year/s (E.g. Lenders Mortgage Insurance)
A103: What was the loan start date | B103: 25/1/2016
A104: What was the total borrowing expense at that time | B104: 5640
A107: New Costs to add to Depreciation and Cap Allowances
A108: Did you incur any costs for a NON-DEDUCTIBLE item costing $300+ or a improvement, renovations etc (not a repair) ?
A109: Add further details or a summary if required. If any costs are included on a QS report do not include them to avoid duplication
A110: Please show the installed cost. Eg Oven $800 + $300 Install = $1100
A111: Advise details: Indicate if item is second hand please
A113: What was cost for | B113: Amount | C113: Date completed
B114: $
B115: $
B116: $
B117: $
B118: $
B119: $
B120: $
A122: Terms & Conditions: © Consulting By PK - All rights reserved. Do not share, copy, reproduce or sell any part of this document unless you have written permission from Consulting By PK. All infringements will be prosecuted. If you are the personal owner of the Consulting By PK End User License then you may use it for your own use but not for any other purpose. Disclaimer: The opinions expressed in all material published by Consulting By PK are not to be construed as financial or investment advice nor should be relied upon for any investment activities. Consulting By PK strongly recommends that you perform your own independent research and/or seek your own legal advice before making any financial decisions. Contents of this message are of general nature only and should not be relied upon solely when making an investment decision. Consulting By PK nor any of its directors, associates, staff, or associated companies bear any liability from any actions derived from in this document. One should always seek third party investment information from relevant parties such as legal, finance, and accountancy enquiries.

Sheet Property 8
A1: Property 8
A3: Estimated Cashflow before tax considerations | B3: =C86+C63 -> -5013.83
A4: Approximate refund due from ATO | B4: =-C86*C4 -> 5648.3571 | C4: 0.37 | D4: < Insert your tax rate
A5: Estimated Cashflow after tax considerations | B5: =B3+B4 -> 634.5271
A8: Address
F9: Guidance Notes
A11: Complete this table in full please :
A12: Date property acquired : | E12: 42394 | F12: Date settled
A13: Do you have a Quantity Surveyor Report (Depreciation Schedule)? | E13: Yes | F13: Ensure accountant is provided with this. Upload ONCE when new OR replaced
A15: If a new IP but not acquired this year, was this a former home ? | E15: Please answer
A16: If so, do you know its market value on the date it first earned rent ? | E16: Please answer | F16: This can affect CGT costbase
A18: If acquired prior to this tax year - Was property refinanced this year ? | E18: No | F18: Borrowing expenses may be impacted. Refer below
A19: If refinanced this year was the loan increased ? | E19: Please answer | F19: If so, the new loan may be deductible against the new IP or new investment. Or Non-deductible. Info reqd
A21: Is this property NRAS ? | E21: No
A22: If it is, do you have the certificate for annual incentives yet ? | E22: No
A23: What is the State Incentive Amount ? | E23: $
A24: What is the Commonwealth Tax Credit Amount ? | E24: $
A26: Since the start of the financial year have you or others ever resided within this property rent free ? | E26: No
A28: Period available to rent in Financial Year | B28: Start | C28: End | F28: Explain if not available for the whole period, Change dates please
A29: Start | B29: 43282 | C29: 43646
A31: Ownership of property | B31: % | F31: Full name/s of all owners and their % share of title is essential
A32: Name of Owner 1 | B32: 1
A33: Name of Owner 2 | B33: 0
A34: Name of Owner 3 | B34: 0
A35: Name of Owner 4 | B35: 0
B36: =SUM(B32:B35) -> 1 | F36: Must add to 100%
A39: Income and Expenses Summary for this property
A41: Rent - Collected by Agent/s | C41: 21820.36 | F41: Generally entered from annual agent summary
A42: Rent - Collected by Owner/s | C42: 0 | F42: This assists accountant to address agent fees inconsistencies etc
A43: Bond retained (damage) NOT bond received for new tenant | C43: 0 | F43: Bond retained for damage etc only. Also show repair costs below.
A44: Insurance claim for lost rent / damage etc | C44: 0 | F44: This is assessable when received. Also sho repair costs. If insurer rectified damage then ignore issue
A45: Letting or other fee paid by tenant (ie water) | C45: 0 | F45: All tenant contributions to costs are to be shown here
A46: Tenant contribution for repairs / Loss | C46: 0 | F46: Ensure the repairs etc is also shown below.
A47: Total Income | C47: =SUM(C41:C46) -> 21820.36
A51: Expenses
A52: Advertising for tenants | C52: 0
A53: Asbestos removal costs | C53: 0 | F53: A specific deduction for removing asbestos may be available
A54: Body Corp / Strata - Ordinary levies | C54: 0 | F54: Do not include strata adjustments on new property acquisition. Include below 2 lines below
A55: Body Corp / Strata - Special levies | C55: 0 | D55: NOT DEDUCTIBLE…………………. | F55: Special levies may increase QS depreciation if amended by QS after completion of works
A56: Body Corp / Strata - For newly acquired property (only) | C56: 0 | F56: New acquisition only. Include strata levy settlement adjustment from lawyers settlement here
A57: Borrowing Expenses - Annual Loyalty / Package Fee | C57: 0 | F57: Show the % of annual fee relating to discounts for this property v's others
A58: Borrowing Expenses - Monthly Fees | C58: 0 | F58: Bank lender monthly fees etc eg $8pm x 12= $96
A59: Break costs (Fixed to variable loan) | C59: 0 | F59: Deductible unless broken to dispose of property. Discuss
A60: Cleaning, waste and rubbish removal | C60: 0 | F60: Not for initial tenancy. Between or after tenancy
A61: Council rates | C61: 2624.3 | F61: Do not include rates adjustments on new acquisitions here. Include next row
A62: Council rates - For newly acquired property (only) | C62: 0 | F62: New acquisition only. Include rates adjustment from lawyers settlement here
A63: Depreciation from Quantity Surveyor report | C63: 10252 | F63: Do not include capital allowances (Div 43). Include that below.
A64: Gardens lawns and yard maintenance | C64: 0 | F64: Can include tree removal etc if existing tenancy
A65: Insurance - Building | C65: 1835.51 | F65: Include premiums paid in period. Do not adjust for period of time
A66: Insurance - Contents | C66: 0 | F66: Include premiums paid in period. Do not adjust for period of time
A67: Insurance - Landlord policy | C67: 300.21 | F67: Include premiums paid in period. Do not adjust for period of time
... A74: Pest Control | C74: 0 | F74: Do NOT show initial P&B or initial repairs here
A75: Property Agent (incl GST) incl letting fees | C75: =1855+120+197.5 -> 2172.5
A76: Repairs & Maintenance - Before tenant | C76: 0 | D76: NOT DEDUCTIBLE…………………. | F76: Initial repairs are non-deductible. May be depreciable
A77: Repairs & Maintenance incl Tenant damage / wear | C77: 2448.7 | F77: Do NOT include depreciable items replaced here
A78: Quantity Surveyor Report Fee | C78: 0 | F78: Only show cost if a new report was obtained and paid this tax year
A79: Stationery, Phone, Post etc | C79: 100
A80: Travel - Any purpose, any reason = Non-deductible | D80: NOT DEDUCTIBLE…………………. | F80: Travel cannot be included in capital costs, deductions or repair costs
A81: Water | C81: 119 | F81: Include costs paid. If tenant reimbursed include that as income. Incl QLD fee for reading
A82: Water - For newly acquired property (only) | C82: 0 | F82: New acquisition only. Include upwards water adjustment from lawyers settlement here
A83: Sundry Costs | C83: 0 | F83: Details :
A84: Total Expenses | C84: =SUM(C52:C83) -> 37086.19
A86: Estimated Profit (Loss) before tax considerations | C86: =(C47-C84) -> -15265.83
A89: Borrowing Expenses
A91: Refinance Expenses (this financial year). For new acquisitions please provide lender information instead
A92: Did you refinance a former loan ? | B92: No
A93: Is the loan amount the same as previously | B93: Yes | C93: Answers No may be incorrect unless new funds were to improve or renovate.
A94: Total loan fees incurred to refinance this | B94: $ | C94: (If the refinance was to buy a new property the costs may need be applied to that new property instead of this property)
A95: Was there a break cost for THIS loan | B95: $ | C95: Eg Break a fixed loan
A97: New finance fees - For a new property generally. If new borrowing for new IP using equity include on THAT property. Not here
A98: Total borrowing expenses | B98: $ | C98: Include ALL bank fees for the loan incl appn, broker, valuation, legals by bank and LMI. Provide accountant with lender letter
A99: Is loan term greater than 5 years ? | B99: Yes | C99: Accountant will calculate a deduction based on loan term OR 60 months (shorter) and include a schedule in return.
C100: Do NOT include stamp duty or property settlement legal costs
A102: Borrowing Expenses from prior year/s (E.g. Lenders Mortgage Insurance)
A103: What was the loan start date | B103: 25/1/2016
A104: What was the total borrowing expense at that time | B104: 5640
A107: New Costs to add to Depreciation and Cap Allowances
A108: Did you incur any costs for a NON-DEDUCTIBLE item costing $300+ or a improvement, renovations etc (not a repair) ?
A109: Add further details or a summary if required. If any costs are included on a QS report do not include them to avoid duplication
A110: Please show the installed cost. Eg Oven $800 + $300 Install = $1100
A111: Advise details: Indicate if item is second hand please
A113: What was cost for | B113: Amount | C113: Date completed
B114: $
B115: $
B116: $
B117: $
B118: $
B119: $
B120: $
A122: Terms & Conditions: © Consulting By PK - All rights reserved. Do not share, copy, reproduce or sell any part of this document unless you have written permission from Consulting By PK. All infringements will be prosecuted. If you are the personal owner of the Consulting By PK End User License then you may use it for your own use but not for any other purpose. Disclaimer: The opinions expressed in all material published by Consulting By PK are not to be construed as financial or investment advice nor should be relied upon for any investment activities. Consulting By PK strongly recommends that you perform your own independent research and/or seek your own legal advice before making any financial decisions. Contents of this message are of general nature only and should not be relied upon solely when making an investment decision. Consulting By PK nor any of its directors, associates, staff, or associated companies bear any liability from any actions derived from in this document. One should always seek third party investment information from relevant parties such as legal, finance, and accountancy enquiries.

Sheet Property 9
A1: Property 9
A3: Estimated Cashflow before tax considerations | B3: =C86+C63 -> -5013.83
A4: Approximate refund due from ATO | B4: =-C86*C4 -> 5648.3571 | C4: 0.37 | D4: < Insert your tax rate
A5: Estimated Cashflow after tax considerations | B5: =B3+B4 -> 634.5271
A8: Address
F9: Guidance Notes
A11: Complete this table in full please :
A12: Date property acquired : | E12: 42394 | F12: Date settled
A13: Do you have a Quantity Surveyor Report (Depreciation Schedule)? | E13: Yes | F13: Ensure accountant is provided with this. Upload ONCE when new OR replaced
A15: If a new IP but not acquired this year, was this a former home ? | E15: Please answer
A16: If so, do you know its market value on the date it first earned rent ? | E16: Please answer | F16: This can affect CGT costbase
A18: If acquired prior to this tax year - Was property refinanced this year ? | E18: No | F18: Borrowing expenses may be impacted. Refer below
A19: If refinanced this year was the loan increased ? | E19: Please answer | F19: If so, the new loan may be deductible against the new IP or new investment. Or Non-deductible. Info reqd
A21: Is this property NRAS ? | E21: No
A22: If it is, do you have the certificate for annual incentives yet ? | E22: No
A23: What is the State Incentive Amount ? | E23: $
A24: What is the Commonwealth Tax Credit Amount ? | E24: $
A26: Since the start of the financial year have you or others ever resided within this property rent free ? | E26: No
A28: Period available to rent in Financial Year | B28: Start | C28: End | F28: Explain if not available for the whole period, Change dates please
A29: Start | B29: 43282 | C29: 43646
A31: Ownership of property | B31: % | F31: Full name/s of all owners and their % share of title is essential
A32: Name of Owner 1 | B32: 1
A33: Name of Owner 2 | B33: 0
A34: Name of Owner 3 | B34: 0
A35: Name of Owner 4 | B35: 0
B36: =SUM(B32:B35) -> 1 | F36: Must add to 100%
A39: Income and Expenses Summary for this property
A41: Rent - Collected by Agent/s | C41: 21820.36 | F41: Generally entered from annual agent summary
A42: Rent - Collected by Owner/s | C42: 0 | F42: This assists accountant to address agent fees inconsistencies etc
A43: Bond retained (damage) NOT bond received for new tenant | C43: 0 | F43: Bond retained for damage etc only. Also show repair costs below.
A44: Insurance claim for lost rent / damage etc | C44: 0 | F44: This is assessable when received. Also sho repair costs. If insurer rectified damage then ignore issue
A45: Letting or other fee paid by tenant (ie water) | C45: 0 | F45: All tenant contributions to costs are to be shown here
A46: Tenant contribution for repairs / Loss | C46: 0 | F46: Ensure the repairs etc is also shown below.
A47: Total Income | C47: =SUM(C41:C46) -> 21820.36
A51: Expenses
A52: Advertising for tenants | C52: 0
A53: Asbestos removal costs | C53: 0 | F53: A specific deduction for removing asbestos may be available
A54: Body Corp / Strata - Ordinary levies | C54: 0 | F54: Do not include strata adjustments on new property acquisition. Include below 2 lines below
A55: Body Corp / Strata - Special levies | C55: 0 | D55: NOT DEDUCTIBLE…………………. | F55: Special levies may increase QS depreciation if amended by QS after completion of works
A56: Body Corp / Strata - For newly acquired property (only) | C56: 0 | F56: New acquisition only. Include strata levy settlement adjustment from lawyers settlement here
A57: Borrowing Expenses - Annual Loyalty / Package Fee | C57: 0 | F57: Show the % of annual fee relating to discounts for this property v's others
A58: Borrowing Expenses - Monthly Fees | C58: 0 | F58: Bank lender monthly fees etc eg $8pm x 12= $96
A59: Break costs (Fixed to variable loan) | C59: 0 | F59: Deductible unless broken to dispose of property. Discuss
A60: Cleaning, waste and rubbish removal | C60: 0 | F60: Not for initial tenancy. Between or after tenancy
A61: Council rates | C61: 2624.3 | F61: Do not include rates adjustments on new acquisitions here. Include next row
A62: Council rates - For newly acquired property (only) | C62: 0 | F62: New acquisition only. Include rates adjustment from lawyers settlement here
A63: Depreciation from Quantity Surveyor report | C63: 10252 | F63: Do not include capital allowances (Div 43). Include that below.
A64: Gardens lawns and yard maintenance | C64: 0 | F64: Can include tree removal etc if existing tenancy
A65: Insurance - Building | C65: 1835.51 | F65: Include premiums paid in period. Do not adjust for period of time
A66: Insurance - Contents | C66: 0 | F66: Include premiums paid in period. Do not adjust for period of time
A67: Insurance - Landlord policy | C67: 300.21 | F67: Include premiums paid in period. Do not adjust for period of time
... A74: Pest Control | C74: 0 | F74: Do NOT show initial P&B or initial repairs here
A75: Property Agent (incl GST) incl letting fees | C75: =1855+120+197.5 -> 2172.5
A76: Repairs & Maintenance - Before tenant | C76: 0 | D76: NOT DEDUCTIBLE…………………. | F76: Initial repairs are non-deductible. May be depreciable
A77: Repairs & Maintenance incl Tenant damage / wear | C77: 2448.7 | F77: Do NOT include depreciable items replaced here
A78: Quantity Surveyor Report Fee | C78: 0 | F78: Only show cost if a new report was obtained and paid this tax year
A79: Stationery, Phone, Post etc | C79: 100
A80: Travel - Any purpose, any reason = Non-deductible | D80: NOT DEDUCTIBLE…………………. | F80: Travel cannot be included in capital costs, deductions or repair costs
A81: Water | C81: 119 | F81: Include costs paid. If tenant reimbursed include that as income. Incl QLD fee for reading
A82: Water - For newly acquired property (only) | C82: 0 | F82: New acquisition only. Include upwards water adjustment from lawyers settlement here
A83: Sundry Costs | C83: 0 | F83: Details :
A84: Total Expenses | C84: =SUM(C52:C83) -> 37086.19
A86: Estimated Profit (Loss) before tax considerations | C86: =(C47-C84) -> -15265.83
A89: Borrowing Expenses
A91: Refinance Expenses (this financial year). For new acquisitions please provide lender information instead
A92: Did you refinance a former loan ? | B92: No
A93: Is the loan amount the same as previously | B93: Yes | C93: Answers No may be incorrect unless new funds were to improve or renovate.
A94: Total loan fees incurred to refinance this | B94: $ | C94: (If the refinance was to buy a new property the costs may need be applied to that new property instead of this property)
A95: Was there a break cost for THIS loan | B95: $ | C95: Eg Break a fixed loan
A97: New finance fees - For a new property generally. If new borrowing for new IP using equity include on THAT property. Not here
A98: Total borrowing expenses | B98: $ | C98: Include ALL bank fees for the loan incl appn, broker, valuation, legals by bank and LMI. Provide accountant with lender letter
A99: Is loan term greater than 5 years ? | B99: Yes | C99: Accountant will calculate a deduction based on loan term OR 60 months (shorter) and include a schedule in return.
C100: Do NOT include stamp duty or property settlement legal costs
A102: Borrowing Expenses from prior year/s (E.g. Lenders Mortgage Insurance)
A103: What was the loan start date | B103: 25/1/2016
A104: What was the total borrowing expense at that time | B104: 5640
A107: New Costs to add to Depreciation and Cap Allowances
A108: Did you incur any costs for a NON-DEDUCTIBLE item costing $300+ or a improvement, renovations etc (not a repair) ?
A109: Add further details or a summary if required. If any costs are included on a QS report do not include them to avoid duplication
A110: Please show the installed cost. Eg Oven $800 + $300 Install = $1100
A111: Advise details: Indicate if item is second hand please
A113: What was cost for | B113: Amount | C113: Date completed
B114: $
B115: $
B116: $
B117: $
B118: $
B119: $
B120: $
A122: Terms & Conditions: © Consulting By PK - All rights reserved. Do not share, copy, reproduce or sell any part of this document unless you have written permission from Consulting By PK. All infringements will be prosecuted. If you are the personal owner of the Consulting By PK End User License then you may use it for your own use but not for any other purpose. Disclaimer: The opinions expressed in all material published by Consulting By PK are not to be construed as financial or investment advice nor should be relied upon for any investment activities. Consulting By PK strongly recommends that you perform your own independent research and/or seek your own legal advice before making any financial decisions. Contents of this message are of general nature only and should not be relied upon solely when making an investment decision. Consulting By PK nor any of its directors, associates, staff, or associated companies bear any liability from any actions derived from in this document. One should always seek third party investment information from relevant parties such as legal, finance, and accountancy enquiries.

Sheet Property 10
A1: Property 10
A3: Estimated Cashflow before tax considerations | B3: =C86+C63 -> -5013.83
A4: Approximate refund due from ATO | B4: =-C86*C4 -> 5648.3571 | C4: 0.37 | D4: < Insert your tax rate
A5: Estimated Cashflow after tax considerations | B5: =B3+B4 -> 634.5271
A8: Address
F9: Guidance Notes
A11: Complete this table in full please :
A12: Date property acquired : | E12: 42394 | F12: Date settled
A13: Do you have a Quantity Surveyor Report (Depreciation Schedule)? | E13: Yes | F13: Ensure accountant is provided with this. Upload ONCE when new OR replaced
A15: If a new IP but not acquired this year, was this a former home ? | E15: Please answer
A16: If so, do you know its market value on the date it first earned rent ? | E16: Please answer | F16: This can affect CGT costbase
A18: If acquired prior to this tax year - Was property refinanced this year ? | E18: No | F18: Borrowing expenses may be impacted. Refer below
A19: If refinanced this year was the loan increased ? | E19: Please answer | F19: If so, the new loan may be deductible against the new IP or new investment. Or Non-deductible. Info reqd
A21: Is this property NRAS ? | E21: No
A22: If it is, do you have the certificate for annual incentives yet ? | E22: No
A23: What is the State Incentive Amount ? | E23: $
A24: What is the Commonwealth Tax Credit Amount ? | E24: $
A26: Since the start of the financial year have you or others ever resided within this property rent free ? | E26: No
A28: Period available to rent in Financial Year | B28: Start | C28: End | F28: Explain if not available for the whole period, Change dates please
A29: Start | B29: 43282 | C29: 43646
A31: Ownership of property | B31: % | F31: Full name/s of all owners and their % share of title is essential
A32: Name of Owner 1 | B32: 1
A33: Name of Owner 2 | B33: 0
A34: Name of Owner 3 | B34: 0
A35: Name of Owner 4 | B35: 0
B36: =SUM(B32:B35) -> 1 | F36: Must add to 100%
A39: Income and Expenses Summary for this property
A41: Rent - Collected by Agent/s | C41: 21820.36 | F41: Generally entered from annual agent summary
A42: Rent - Collected by Owner/s | C42: 0 | F42: This assists accountant to address agent fees inconsistencies etc
A43: Bond retained (damage) NOT bond received for new tenant | C43: 0 | F43: Bond retained for damage etc only. Also show repair costs below.
A44: Insurance claim for lost rent / damage etc | C44: 0 | F44: This is assessable when received. Also sho repair costs. If insurer rectified damage then ignore issue
A45: Letting or other fee paid by tenant (ie water) | C45: 0 | F45: All tenant contributions to costs are to be shown here
A46: Tenant contribution for repairs / Loss | C46: 0 | F46: Ensure the repairs etc is also shown below.
A47: Total Income | C47: =SUM(C41:C46) -> 21820.36
A51: Expenses
A52: Advertising for tenants | C52: 0
A53: Asbestos removal costs | C53: 0 | F53: A specific deduction for removing asbestos may be available
A54: Body Corp / Strata - Ordinary levies | C54: 0 | F54: Do not include strata adjustments on new property acquisition. Include below 2 lines below
A55: Body Corp / Strata - Special levies | C55: 0 | D55: NOT DEDUCTIBLE…………………. | F55: Special levies may increase QS depreciation if amended by QS after completion of works
A56: Body Corp / Strata - For newly acquired property (only) | C56: 0 | F56: New acquisition only. Include strata levy settlement adjustment from lawyers settlement here
A57: Borrowing Expenses - Annual Loyalty / Package Fee | C57: 0 | F57: Show the % of annual fee relating to discounts for this property v's others
A58: Borrowing Expenses - Monthly Fees | C58: 0 | F58: Bank lender monthly fees etc eg $8pm x 12= $96
A59: Break costs (Fixed to variable loan) | C59: 0 | F59: Deductible unless broken to dispose of property. Discuss
A60: Cleaning, waste and rubbish removal | C60: 0 | F60: Not for initial tenancy. Between or after tenancy
A61: Council rates | C61: 2624.3 | F61: Do not include rates adjustments on new acquisitions here. Include next row
A62: Council rates - For newly acquired property (only) | C62: 0 | F62: New acquisition only. Include rates adjustment from lawyers settlement here
A63: Depreciation from Quantity Surveyor report | C63: 10252 | F63: Do not include capital allowances (Div 43). Include that below.
A64: Gardens lawns and yard maintenance | C64: 0 | F64: Can include tree removal etc if existing tenancy
A65: Insurance - Building | C65: 1835.51 | F65: Include premiums paid in period. Do not adjust for period of time
A66: Insurance - Contents | C66: 0 | F66: Include premiums paid in period. Do not adjust for period of time
A67: Insurance - Landlord policy | C67: 300.21 | F67: Include premiums paid in period. Do not adjust for period of time
... A74: Pest Control | C74: 0 | F74: Do NOT show initial P&B or initial repairs here
A75: Property Agent (incl GST) incl letting fees | C75: =1855+120+197.5 -> 2172.5
A76: Repairs & Maintenance - Before tenant | C76: 0 | D76: NOT DEDUCTIBLE…………………. | F76: Initial repairs are non-deductible. May be depreciable
A77: Repairs & Maintenance incl Tenant damage / wear | C77: 2448.7 | F77: Do NOT include depreciable items replaced here
A78: Quantity Surveyor Report Fee | C78: 0 | F78: Only show cost if a new report was obtained and paid this tax year
A79: Stationery, Phone, Post etc | C79: 100
A80: Travel - Any purpose, any reason = Non-deductible | D80: NOT DEDUCTIBLE…………………. | F80: Travel cannot be included in capital costs, deductions or repair costs
A81: Water | C81: 119 | F81: Include costs paid. If tenant reimbursed include that as income. Incl QLD fee for reading
A82: Water - For newly acquired property (only) | C82: 0 | F82: New acquisition only. Include upwards water adjustment from lawyers settlement here
A83: Sundry Costs | C83: 0 | F83: Details :
A84: Total Expenses | C84: =SUM(C52:C83) -> 37086.19
A86: Estimated Profit (Loss) before tax considerations | C86: =(C47-C84) -> -15265.83
A89: Borrowing Expenses
A91: Refinance Expenses (this financial year). For new acquisitions please provide lender information instead
A92: Did you refinance a former loan ? | B92: No
A93: Is the loan amount the same as previously | B93: Yes | C93: Answers No may be incorrect unless new funds were to improve or renovate.
A94: Total loan fees incurred to refinance this | B94: $ | C94: (If the refinance was to buy a new property the costs may need be applied to that new property instead of this property)
A95: Was there a break cost for THIS loan | B95: $ | C95: Eg Break a fixed loan
A97: New finance fees - For a new property generally. If new borrowing for new IP using equity include on THAT property. Not here
A98: Total borrowing expenses | B98: $ | C98: Include ALL bank fees for the loan incl appn, broker, valuation, legals by bank and LMI. Provide accountant with lender letter
A99: Is loan term greater than 5 years ? | B99: Yes | C99: Accountant will calculate a deduction based on loan term OR 60 months (shorter) and include a schedule in return.
C100: Do NOT include stamp duty or property settlement legal costs
A102: Borrowing Expenses from prior year/s (E.g. Lenders Mortgage Insurance)
A103: What was the loan start date | B103: 25/1/2016
A104: What was the total borrowing expense at that time | B104: 5640
A107: New Costs to add to Depreciation and Cap Allowances
A108: Did you incur any costs for a NON-DEDUCTIBLE item costing $300+ or a improvement, renovations etc (not a repair) ?
A109: Add further details or a summary if required. If any costs are included on a QS report do not include them to avoid duplication
A110: Please show the installed cost. Eg Oven $800 + $300 Install = $1100
A111: Advise details: Indicate if item is second hand please
A113: What was cost for | B113: Amount | C113: Date completed
B114: $
B115: $
B116: $
B117: $
B118: $
B119: $
B120: $
A122: Terms & Conditions: © Consulting By PK - All rights reserved. Do not share, copy, reproduce or sell any part of this document unless you have written permission from Consulting By PK. All infringements will be prosecuted. If you are the personal owner of the Consulting By PK End User License then you may use it for your own use but not for any other purpose. Disclaimer: The opinions expressed in all material published by Consulting By PK are not to be construed as financial or investment advice nor should be relied upon for any investment activities. Consulting By PK strongly recommends that you perform your own independent research and/or seek your own legal advice before making any financial decisions. Contents of this message are of general nature only and should not be relied upon solely when making an investment decision. Consulting By PK nor any of its directors, associates, staff, or associated companies bear any liability from any actions derived from in this document. One should always seek third party investment information from relevant parties such as legal, finance, and accountancy enquiries.

Sheet Property 11
A1: Property 11
A3: Estimated Cashflow before tax considerations | B3: =C86+C63 -> -5013.83
A4: Approximate refund due from ATO | B4: =-C86*C4 -> 5648.3571 | C4: 0.37 | D4: < Insert your tax rate
A5: Estimated Cashflow after tax considerations | B5: =B3+B4 -> 634.5271
A8: Address
F9: Guidance Notes
A11: Complete this table in full please :
A12: Date property acquired : | E12: 42394 | F12: Date settled
A13: Do you have a Quantity Surveyor Report (Depreciation Schedule)? | E13: Yes | F13: Ensure accountant is provided with this. Upload ONCE when new OR replaced
A15: If a new IP but not acquired this year, was this a former home ? | E15: Please answer
A16: If so, do you know its market value on the date it first earned rent ? | E16: Please answer | F16: This can affect CGT costbase
A18: If acquired prior to this tax year - Was property refinanced this year ? | E18: No | F18: Borrowing expenses may be impacted. Refer below
A19: If refinanced this year was the loan increased ? | E19: Please answer | F19: If so, the new loan may be deductible against the new IP or new investment. Or Non-deductible. Info reqd
A21: Is this property NRAS ? | E21: No
A22: If it is, do you have the certificate for annual incentives yet ? | E22: No
A23: What is the State Incentive Amount ? | E23: $
A24: What is the Commonwealth Tax Credit Amount ? | E24: $
A26: Since the start of the financial year have you or others ever resided within this property rent free ? | E26: No
A28: Period available to rent in Financial Year | B28: Start | C28: End | F28: Explain if not available for the whole period, Change dates please
A29: Start | B29: 43282 | C29: 43646
A31: Ownership of property | B31: % | F31: Full name/s of all owners and their % share of title is essential
A32: Name of Owner 1 | B32: 1
A33: Name of Owner 2 | B33: 0
A34: Name of Owner 3 | B34: 0
A35: Name of Owner 4 | B35: 0
B36: =SUM(B32:B35) -> 1 | F36: Must add to 100%
A39: Income and Expenses Summary for this property
A41: Rent - Collected by Agent/s | C41: 21820.36 | F41: Generally entered from annual agent summary
A42: Rent - Collected by Owner/s | C42: 0 | F42: This assists accountant to address agent fees inconsistencies etc
A43: Bond retained (damage) NOT bond received for new tenant | C43: 0 | F43: Bond retained for damage etc only. Also show repair costs below.
A44: Insurance claim for lost rent / damage etc | C44: 0 | F44: This is assessable when received. Also sho repair costs. If insurer rectified damage then ignore issue
A45: Letting or other fee paid by tenant (ie water) | C45: 0 | F45: All tenant contributions to costs are to be shown here
A46: Tenant contribution for repairs / Loss | C46: 0 | F46: Ensure the repairs etc is also shown below.
A47: Total Income | C47: =SUM(C41:C46) -> 21820.36
A51: Expenses
A52: Advertising for tenants | C52: 0
A53: Asbestos removal costs | C53: 0 | F53: A specific deduction for removing asbestos may be available
A54: Body Corp / Strata - Ordinary levies | C54: 0 | F54: Do not include strata adjustments on new property acquisition. Include below 2 lines below
A55: Body Corp / Strata - Special levies | C55: 0 | D55: NOT DEDUCTIBLE…………………. | F55: Special levies may increase QS depreciation if amended by QS after completion of works
A56: Body Corp / Strata - For newly acquired property (only) | C56: 0 | F56: New acquisition only. Include strata levy settlement adjustment from lawyers settlement here
A57: Borrowing Expenses - Annual Loyalty / Package Fee | C57: 0 | F57: Show the % of annual fee relating to discounts for this property v's others
A58: Borrowing Expenses - Monthly Fees | C58: 0 | F58: Bank lender monthly fees etc eg $8pm x 12= $96
A59: Break costs (Fixed to variable loan) | C59: 0 | F59: Deductible unless broken to dispose of property. Discuss
A60: Cleaning, waste and rubbish removal | C60: 0 | F60: Not for initial tenancy. Between or after tenancy
A61: Council rates | C61: 2624.3 | F61: Do not include rates adjustments on new acquisitions here. Include next row
A62: Council rates - For newly acquired property (only) | C62: 0 | F62: New acquisition only. Include rates adjustment from lawyers settlement here
A63: Depreciation from Quantity Surveyor report | C63: 10252 | F63: Do not include capital allowances (Div 43). Include that below.
A64: Gardens lawns and yard maintenance | C64: 0 | F64: Can include tree removal etc if existing tenancy
A65: Insurance - Building | C65: 1835.51 | F65: Include premiums paid in period. Do not adjust for period of time
A66: Insurance - Contents | C66: 0 | F66: Include premiums paid in period. Do not adjust for period of time
A67: Insurance - Landlord policy | C67: 300.21 | F67: Include premiums paid in period. Do not adjust for period of time
... A74: Pest Control | C74: 0 | F74: Do NOT show initial P&B or initial repairs here
A75: Property Agent (incl GST) incl letting fees | C75: =1855+120+197.5 -> 2172.5
A76: Repairs & Maintenance - Before tenant | C76: 0 | D76: NOT DEDUCTIBLE…………………. | F76: Initial repairs are non-deductible. May be depreciable
A77: Repairs & Maintenance incl Tenant damage / wear | C77: 2448.7 | F77: Do NOT include depreciable items replaced here
A78: Quantity Surveyor Report Fee | C78: 0 | F78: Only show cost if a new report was obtained and paid this tax year
A79: Stationery, Phone, Post etc | C79: 100
A80: Travel - Any purpose, any reason = Non-deductible | D80: NOT DEDUCTIBLE…………………. | F80: Travel cannot be included in capital costs, deductions or repair costs
A81: Water | C81: 119 | F81: Include costs paid. If tenant reimbursed include that as income. Incl QLD fee for reading
A82: Water - For newly acquired property (only) | C82: 0 | F82: New acquisition only. Include upwards water adjustment from lawyers settlement here
A83: Sundry Costs | C83: 0 | F83: Details :
A84: Total Expenses | C84: =SUM(C52:C83) -> 37086.19
A86: Estimated Profit (Loss) before tax considerations | C86: =(C47-C84) -> -15265.83
A89: Borrowing Expenses
A91: Refinance Expenses (this financial year). For new acquisitions please provide lender information instead
A92: Did you refinance a former loan ? | B92: No
A93: Is the loan amount the same as previously | B93: Yes | C93: Answers No may be incorrect unless new funds were to improve or renovate.
A94: Total loan fees incurred to refinance this | B94: $ | C94: (If the refinance was to buy a new property the costs may need be applied to that new property instead of this property)
A95: Was there a break cost for THIS loan | B95: $ | C95: Eg Break a fixed loan
A97: New finance fees - For a new property generally. If new borrowing for new IP using equity include on THAT property. Not here
A98: Total borrowing expenses | B98: $ | C98: Include ALL bank fees for the loan incl appn, broker, valuation, legals by bank and LMI. Provide accountant with lender letter
A99: Is loan term greater than 5 years ? | B99: Yes | C99: Accountant will calculate a deduction based on loan term OR 60 months (shorter) and include a schedule in return.
C100: Do NOT include stamp duty or property settlement legal costs
A102: Borrowing Expenses from prior year/s (E.g. Lenders Mortgage Insurance)
A103: What was the loan start date | B103: 25/1/2016
A104: What was the total borrowing expense at that time | B104: 5640
A107: New Costs to add to Depreciation and Cap Allowances
A108: Did you incur any costs for a NON-DEDUCTIBLE item costing $300+ or a improvement, renovations etc (not a repair) ?
A109: Add further details or a summary if required. If any costs are included on a QS report do not include them to avoid duplication
A110: Please show the installed cost. Eg Oven $800 + $300 Install = $1100
A111: Advise details: Indicate if item is second hand please
A113: What was cost for | B113: Amount | C113: Date completed
B114: $
B115: $
B116: $
B117: $
B118: $
B119: $
B120: $
A122: Terms & Conditions: © Consulting By PK - All rights reserved. Do not share, copy, reproduce or sell any part of this document unless you have written permission from Consulting By PK. All infringements will be prosecuted. If you are the personal owner of the Consulting By PK End User License then you may use it for your own use but not for any other purpose. Disclaimer: The opinions expressed in all material published by Consulting By PK are not to be construed as financial or investment advice nor should be relied upon for any investment activities. Consulting By PK strongly recommends that you perform your own independent research and/or seek your own legal advice before making any financial decisions. Contents of this message are of general nature only and should not be relied upon solely when making an investment decision. Consulting By PK nor any of its directors, associates, staff, or associated companies bear any liability from any actions derived from in this document. One should always seek third party investment information from relevant parties such as legal, finance, and accountancy enquiries.

Sheet Portfolio Summary
A1: Portfolio Summary
A3: Estimated Cashflow before tax considerations | B3: ='Property 5'!B3+'Property 4'!B3+'Property 3'!B3+'Property 2'!B3+'7 Rosella Close'!B3+'Property 6'!B3+'Property 7'!B3+'Property 8'!B3+'Property 9'!B3+'Property 10'!B3+'Property 11'!B3 -> -55152.13
A4: Approximate refund due from ATO | B4: ='Property 5'!B4+'Property 4'!B4+'Property 3'!B4+'Property 2'!B4+'7 Rosella Close'!B4+'Property 6'!B4+'Property 7'!B4+'Property 8'!B4+'Property 9'!B4+'Property 10'!B4+'Property 11'!B4 -> 62131.928
A5: Estimated Cashflow after tax considerations | B5: ='Property 5'!B5+'Property 4'!B5+'Property 3'!B5+'Property 2'!B5+'7 Rosella Close'!B5+'Property 6'!B5+'Property 7'!B5+'Property 8'!B5+'Property 9'!B5+'Property 10'!B5+'Property 11'!B5 -> 6979.7981
C8: Income | D8: Expenses | E8: Estimated Profit (Loss) before tax considerations
A9: Property 1 | B9: =('7 Rosella Close'!A8) -> 7 Rosella Close, Mount Sheridan QLD 4868 | C9: =('7 Rosella Close'!$C$47) -> 21820.36 | D9: =('7 Rosella Close'!$C$84) -> 37086.19 | E9: =(C9-D9) -> -15265.83
A10: Property 2 | B10: =('Property 2'!A$8) -> Address | C10: =('Property 2'!$C$47) -> 21820.36 | D10: =('Property 2'!$C$84) -> 37086.19 | E10: =(C10-D10) -> -15265.83
A11: Property 3 | B11: =('Property 3'!A$8) -> Address | C11: =('Property 3'!$C$47) -> 21820.36 | D11: =('Property 3'!$C$84) -> 37086.19 | E11: =(C11-D11) -> -15265.83
A12: Property 4 | B12: =('Property 4'!A$8) -> Address | C12: =('Property 4'!$C$47) -> 21820.36 | D12: =('Property 4'!$C$84) -> 37086.19 | E12: =(C12-D12) -> -15265.83
A13: Property 5 | B13: =('Property 5'!A$8) -> Address | C13: =('Property 5'!$C$47) -> 21820.36 | D13: =('Property 5'!$C$84) -> 37086.19 | E13: =(C13-D13) -> -15265.83
A14: Property 6 | B14: ='Property 6'!A8 -> Address | C14: =('Property 6'!$C$47) -> 21820.36 | D14: =('Property 6'!$C$84) -> 37086.19 | E14: =(C14-D14) -> -15265.83
A15: Property 7 | B15: ='Property 7'!A8 -> Address | C15: =('Property 7'!$C$47) -> 21820.36 | D15: =('Property 7'!$C$84) -> 37086.19 | E15: =(C15-D15) -> -15265.83
A16: Property 8 | B16: ='Property 8'!A8 -> Address | C16: =('Property 8'!$C$47) -> 21820.36 | D16: =('Property 8'!$C$84) -> 37086.19 | E16: =(C16-D16) -> -15265.83
A17: Property 9 | B17: ='Property 9'!A8 -> Address | C17: =('Property 9'!$C$47) -> 21820.36 | D17: =('Property 9'!$C$84) -> 37086.19 | E17: =(C17-D17) -> -15265.83
A18: Property 10 | B18: ='Property 10'!A8 -> Address | C18: =('Property 10'!$C$47) -> 21820.36 | D18: =('Property 10'!$C$84) -> 37086.19 | E18: =(C18-D18) -> -15265.83
A19: Property 11 | B19: ='Property 11'!A8 -> Address | C19: =('Property 11'!$C$47) -> 21820.36 | D19: =('Property 11'!$C$84) -> 37086.19 | E19: =(C19-D19) -> -15265.83
C20: =SUM(C9:C19) -> 240023.96 | D20: =SUM(D9:D19) -> 407948.09 | E20: =SUM(E9:E19) -> -167924.13
A22: Other property related deductions that aren't specific to one property
A24: xxx
A25: xxx
A27: xxx
A28: xxx
A30: xxx
A31: xxx
A36: Terms & Conditions: © Consulting By PK - All rights reserved. Do not share, copy, reproduce or sell any part of this document unless you have written permission from Consulting By PK. All infringements will be prosecuted. If you are the personal owner of the Consulting By PK End User License then you may use it for your own use but not for any other purpose. Disclaimer: The opinions expressed in all material published by Consulting By PK are not to be construed as financial or investment advice nor should be relied upon for any investment activities. Consulting By PK strongly recommends that you perform your own independent research and/or seek your own legal advice before making any financial decisions. Contents of this message are of general nature only and should not be relied upon solely when making an investment decision. Consulting By PK nor any of its directors, associates, staff, or associated companies bear any liability from any actions derived from in this document. One should always seek third party investment information from relevant parties such as legal, finance, and accountancy enquiries.
